<?xml version="1.0" encoding="UTF-8"?>
<SunopsisExport>
<Admin RepositoryVersion="05.02.02.09" IsLegacyIdCompatible="false" />
<Encryption algorithm="AES" keyLength="128" exportKeyHash="" keyVect="CpSHzJ06NeOmudxdcMYYhg==" exportKeySalt="f75a1238-4227-4231-8801-a33348231b0e" containsCipherText="false"/>
<Object class="com.sunopsis.dwg.dbobj.SnpTable">
		<Field name="ExtVersion" type="java.lang.String">null</Field>
	<Field name="FileDecSep" type="java.lang.String">null</Field>
	<Field name="FileEncField" type="java.lang.String">null</Field>
	<Field name="FileEscChar" type="java.lang.String">null</Field>
	<Field name="FileFirstRow" type="com.sunopsis.sql.DbInt"><![CDATA[null]]></Field>
	<Field name="FileFormat" type="java.lang.String">null</Field>
	<Field name="FileNullValue" type="java.lang.String">null</Field>
	<Field name="FileSepColl" type="java.lang.String">null</Field>
	<Field name="FileSepField" type="java.lang.String">null</Field>
	<Field name="FileSepMap" type="java.lang.String">null</Field>
	<Field name="FileSepRow" type="java.lang.String">null</Field>
	<Field name="FirstDate" type="java.sql.Timestamp"><![CDATA[2021-05-21 12:32:42.0]]></Field>
	<Field name="FirstUser" type="java.lang.String"><![CDATA[prueba]]></Field>
	<Field name="GlobalId" type="java.lang.String"><![CDATA[394df076-b99a-4538-b912-2f93e9919712]]></Field>
	<Field name="HiveBuckets" type="com.sunopsis.sql.DbInt"><![CDATA[null]]></Field>
	<Field name="HiveLocation" type="java.lang.String">null</Field>
	<Field name="HiveRowFormat" type="java.lang.String">null</Field>
	<Field name="IndChange" type="java.lang.String"><![CDATA[U]]></Field>
	<Field name="IndErrDel" type="java.lang.String">null</Field>
	<Field name="IndFilePosAuto" type="java.lang.String">null</Field>
	<Field name="IndHiveManaged" type="java.lang.String">null</Field>
	<Field name="IndHiveNative" type="java.lang.String">null</Field>
	<Field name="IndJrn" type="java.lang.String"><![CDATA[0]]></Field>
	<Field name="IndShow" type="java.lang.String"><![CDATA[1]]></Field>
	<Field name="IndWs" type="java.lang.String">null</Field>
	<Field name="InputFormat" type="java.lang.String">null</Field>
	<Field name="IntVersion" type="com.sunopsis.sql.DbInt"><![CDATA[1]]></Field>
	<Field name="IMod" type="com.sunopsis.sql.DbInt"><![CDATA[51]]></Field>
	<Field name="IScBaseTable" type="com.sunopsis.sql.DbInt"><![CDATA[null]]></Field>
	<Field name="IScOrigTable" type="com.sunopsis.sql.DbInt"><![CDATA[null]]></Field>
	<Field name="IScTable" type="com.sunopsis.sql.DbInt"><![CDATA[null]]></Field>
	<Field name="ISubModel" type="com.sunopsis.sql.DbInt"><![CDATA[52]]></Field>
	<Field name="ITable" type="com.sunopsis.sql.DbInt"><![CDATA[192]]></Field>
	<Field name="ITableFormatType" type="com.sunopsis.sql.DbInt"><![CDATA[null]]></Field>
	<Field name="ITxtDesc" type="com.sunopsis.sql.DbInt"><![CDATA[null]]></Field>
	<Field name="ITxtWsdl" type="com.sunopsis.sql.DbInt"><![CDATA[null]]></Field>
	<Field name="JrnOrder" type="com.sunopsis.sql.DbInt"><![CDATA[null]]></Field>
	<Field name="LastDate" type="java.sql.Timestamp"><![CDATA[2021-05-21 12:32:43.0]]></Field>
	<Field name="LastUser" type="java.lang.String"><![CDATA[prueba]]></Field>
	<Field name="OlapType" type="java.lang.String">null</Field>
	<Field name="OutputFormat" type="java.lang.String">null</Field>
	<Field name="PartitionMeth" type="java.lang.String">null</Field>
	<Field name="ResName" type="java.lang.String"><![CDATA[ACTIVIDADESBK]]></Field>
	<Field name="RCount" type="com.sunopsis.sql.DbInt"><![CDATA[null]]></Field>
	<Field name="SchemaFile" type="java.lang.String">null</Field>
	<Field name="ScOrigTableTag" type="java.lang.String">null</Field>
	<Field name="Serde" type="java.lang.String">null</Field>
	<Field name="SerdeProp" type="java.lang.String">null</Field>
	<Field name="StorageHandler" type="java.lang.String">null</Field>
	<Field name="StorageProp" type="java.lang.String">null</Field>
	<Field name="SubPartitionMeth" type="java.lang.String">null</Field>
	<Field name="TableAlias" type="java.lang.String"><![CDATA[ACTIVIDADESBK]]></Field>
	<Field name="TableName" type="java.lang.String"><![CDATA[ACTIVIDADESBK]]></Field>
	<Field name="TableProp" type="java.lang.String">null</Field>
	<Field name="TableType" type="java.lang.String"><![CDATA[T]]></Field>
	<Field name="WsEntityName" type="java.lang.String">null</Field>
	<Field name="WsName" type="java.lang.String">null</Field>
</Object>
<Object class="com.sunopsis.dwg.dbobj.SnpCol">
		<Field name="Bytes" type="com.sunopsis.sql.DbInt"><![CDATA[0]]></Field>
	<Field name="CheckFlow" type="java.lang.String"><![CDATA[1]]></Field>
	<Field name="CheckStat" type="java.lang.String"><![CDATA[0]]></Field>
	<Field name="ColDecSep" type="java.lang.String">null</Field>
	<Field name="ColFormat" type="java.lang.String">null</Field>
	<Field name="ColHeading" type="java.lang.String"><![CDATA[ID_DE_ACTIVIDAD]]></Field>
	<Field name="ColMandatory" type="java.lang.String"><![CDATA[0]]></Field>
	<Field name="ColName" type="java.lang.String"><![CDATA[ID_DE_ACTIVIDAD]]></Field>
	<Field name="ColNullIfErr" type="java.lang.String">null</Field>
	<Field name="DataFormat" type="java.lang.String">null</Field>
	<Field name="DefValue" type="java.lang.String">null</Field>
	<Field name="ExtVersion" type="java.lang.String">null</Field>
	<Field name="FilePos" type="com.sunopsis.sql.DbInt"><![CDATA[null]]></Field>
	<Field name="FirstDate" type="java.sql.Timestamp"><![CDATA[2021-05-21 12:32:43.0]]></Field>
	<Field name="FirstUser" type="java.lang.String"><![CDATA[prueba]]></Field>
	<Field name="GlobalId" type="java.lang.String"><![CDATA[9f1f053d-d35c-4e54-ba99-7daea3a48e8e]]></Field>
	<Field name="HbaseEncoding" type="java.lang.String">null</Field>
	<Field name="HiveSortbyPos" type="com.sunopsis.sql.DbInt"><![CDATA[null]]></Field>
	<Field name="IndChange" type="java.lang.String"><![CDATA[I]]></Field>
	<Field name="IndHiveCluster" type="java.lang.String">null</Field>
	<Field name="IndHivePartition" type="java.lang.String">null</Field>
	<Field name="IndHiveSort" type="java.lang.String">null</Field>
	<Field name="IndHiveSortbyAsc" type="java.lang.String">null</Field>
	<Field name="IndIn" type="java.lang.String">null</Field>
	<Field name="IndOut" type="java.lang.String">null</Field>
	<Field name="IndWrite" type="java.lang.String"><![CDATA[1]]></Field>
	<Field name="IndWsInsert" type="java.lang.String"><![CDATA[1]]></Field>
	<Field name="IndWsSelect" type="java.lang.String"><![CDATA[1]]></Field>
	<Field name="IndWsUpdate" type="java.lang.String"><![CDATA[1]]></Field>
	<Field name="IntVersion" type="com.sunopsis.sql.DbInt"><![CDATA[1]]></Field>
	<Field name="ICol" type="com.sunopsis.sql.DbInt"><![CDATA[1650]]></Field>
	<Field name="ISrcCol" type="com.sunopsis.sql.DbInt"><![CDATA[null]]></Field>
	<Field name="ITable" type="com.sunopsis.sql.DbInt"><![CDATA[192]]></Field>
	<Field name="ITxtColDesc" type="com.sunopsis.sql.DbInt"><![CDATA[null]]></Field>
	<Field name="LastDate" type="java.sql.Timestamp"><![CDATA[2021-05-21 12:32:43.0]]></Field>
	<Field name="LastUser" type="java.lang.String"><![CDATA[prueba]]></Field>
	<Field name="Longc" type="com.sunopsis.sql.DbInt"><![CDATA[38]]></Field>
	<Field name="Pos" type="com.sunopsis.sql.DbInt"><![CDATA[1]]></Field>
	<Field name="RecCodeList" type="java.lang.String">null</Field>
	<Field name="Scalec" type="com.sunopsis.sql.DbInt"><![CDATA[0]]></Field>
	<Field name="ScdColType" type="java.lang.String">null</Field>
	<Field name="SourceDt" type="java.lang.String"><![CDATA[NUMBER]]></Field>
</Object>
<Object class="com.sunopsis.dwg.dbobj.SnpCol">
		<Field name="Bytes" type="com.sunopsis.sql.DbInt"><![CDATA[0]]></Field>
	<Field name="CheckFlow" type="java.lang.String"><![CDATA[1]]></Field>
	<Field name="CheckStat" type="java.lang.String"><![CDATA[0]]></Field>
	<Field name="ColDecSep" type="java.lang.String">null</Field>
	<Field name="ColFormat" type="java.lang.String">null</Field>
	<Field name="ColHeading" type="java.lang.String"><![CDATA[TIPO_DE_TRABAJO_DE_ACTIVIDAD]]></Field>
	<Field name="ColMandatory" type="java.lang.String"><![CDATA[0]]></Field>
	<Field name="ColName" type="java.lang.String"><![CDATA[TIPO_DE_TRABAJO_DE_ACTIVIDAD]]></Field>
	<Field name="ColNullIfErr" type="java.lang.String">null</Field>
	<Field name="DataFormat" type="java.lang.String">null</Field>
	<Field name="DefValue" type="java.lang.String">null</Field>
	<Field name="ExtVersion" type="java.lang.String">null</Field>
	<Field name="FilePos" type="com.sunopsis.sql.DbInt"><![CDATA[null]]></Field>
	<Field name="FirstDate" type="java.sql.Timestamp"><![CDATA[2021-05-21 12:32:43.0]]></Field>
	<Field name="FirstUser" type="java.lang.String"><![CDATA[prueba]]></Field>
	<Field name="GlobalId" type="java.lang.String"><![CDATA[ce7bee15-6ee5-4d05-806b-17c674d9a2d4]]></Field>
	<Field name="HbaseEncoding" type="java.lang.String">null</Field>
	<Field name="HiveSortbyPos" type="com.sunopsis.sql.DbInt"><![CDATA[null]]></Field>
	<Field name="IndChange" type="java.lang.String"><![CDATA[I]]></Field>
	<Field name="IndHiveCluster" type="java.lang.String">null</Field>
	<Field name="IndHivePartition" type="java.lang.String">null</Field>
	<Field name="IndHiveSort" type="java.lang.String">null</Field>
	<Field name="IndHiveSortbyAsc" type="java.lang.String">null</Field>
	<Field name="IndIn" type="java.lang.String">null</Field>
	<Field name="IndOut" type="java.lang.String">null</Field>
	<Field name="IndWrite" type="java.lang.String"><![CDATA[1]]></Field>
	<Field name="IndWsInsert" type="java.lang.String"><![CDATA[1]]></Field>
	<Field name="IndWsSelect" type="java.lang.String"><![CDATA[1]]></Field>
	<Field name="IndWsUpdate" type="java.lang.String"><![CDATA[1]]></Field>
	<Field name="IntVersion" type="com.sunopsis.sql.DbInt"><![CDATA[1]]></Field>
	<Field name="ICol" type="com.sunopsis.sql.DbInt"><![CDATA[1662]]></Field>
	<Field name="ISrcCol" type="com.sunopsis.sql.DbInt"><![CDATA[null]]></Field>
	<Field name="ITable" type="com.sunopsis.sql.DbInt"><![CDATA[192]]></Field>
	<Field name="ITxtColDesc" type="com.sunopsis.sql.DbInt"><![CDATA[null]]></Field>
	<Field name="LastDate" type="java.sql.Timestamp"><![CDATA[2021-05-21 12:32:43.0]]></Field>
	<Field name="LastUser" type="java.lang.String"><![CDATA[prueba]]></Field>
	<Field name="Longc" type="com.sunopsis.sql.DbInt"><![CDATA[4000]]></Field>
	<Field name="Pos" type="com.sunopsis.sql.DbInt"><![CDATA[2]]></Field>
	<Field name="RecCodeList" type="java.lang.String">null</Field>
	<Field name="Scalec" type="com.sunopsis.sql.DbInt"><![CDATA[null]]></Field>
	<Field name="ScdColType" type="java.lang.String">null</Field>
	<Field name="SourceDt" type="java.lang.String"><![CDATA[VARCHAR2]]></Field>
</Object>
<Object class="com.sunopsis.dwg.dbobj.SnpCol">
		<Field name="Bytes" type="com.sunopsis.sql.DbInt"><![CDATA[0]]></Field>
	<Field name="CheckFlow" type="java.lang.String"><![CDATA[1]]></Field>
	<Field name="CheckStat" type="java.lang.String"><![CDATA[0]]></Field>
	<Field name="ColDecSep" type="java.lang.String">null</Field>
	<Field name="ColFormat" type="java.lang.String">null</Field>
	<Field name="ColHeading" type="java.lang.String"><![CDATA[SUBTIPO_DE_LA_ORDEN_DE_TRABAJ]]></Field>
	<Field name="ColMandatory" type="java.lang.String"><![CDATA[0]]></Field>
	<Field name="ColName" type="java.lang.String"><![CDATA[SUBTIPO_DE_LA_ORDEN_DE_TRABAJ]]></Field>
	<Field name="ColNullIfErr" type="java.lang.String">null</Field>
	<Field name="DataFormat" type="java.lang.String">null</Field>
	<Field name="DefValue" type="java.lang.String">null</Field>
	<Field name="ExtVersion" type="java.lang.String">null</Field>
	<Field name="FilePos" type="com.sunopsis.sql.DbInt"><![CDATA[null]]></Field>
	<Field name="FirstDate" type="java.sql.Timestamp"><![CDATA[2021-05-21 12:32:43.0]]></Field>
	<Field name="FirstUser" type="java.lang.String"><![CDATA[prueba]]></Field>
	<Field name="GlobalId" type="java.lang.String"><![CDATA[273788b5-273d-49c1-9f33-f07753e118e0]]></Field>
	<Field name="HbaseEncoding" type="java.lang.String">null</Field>
	<Field name="HiveSortbyPos" type="com.sunopsis.sql.DbInt"><![CDATA[null]]></Field>
	<Field name="IndChange" type="java.lang.String"><![CDATA[I]]></Field>
	<Field name="IndHiveCluster" type="java.lang.String">null</Field>
	<Field name="IndHivePartition" type="java.lang.String">null</Field>
	<Field name="IndHiveSort" type="java.lang.String">null</Field>
	<Field name="IndHiveSortbyAsc" type="java.lang.String">null</Field>
	<Field name="IndIn" type="java.lang.String">null</Field>
	<Field name="IndOut" type="java.lang.String">null</Field>
	<Field name="IndWrite" type="java.lang.String"><![CDATA[1]]></Field>
	<Field name="IndWsInsert" type="java.lang.String"><![CDATA[1]]></Field>
	<Field name="IndWsSelect" type="java.lang.String"><![CDATA[1]]></Field>
	<Field name="IndWsUpdate" type="java.lang.String"><![CDATA[1]]></Field>
	<Field name="IntVersion" type="com.sunopsis.sql.DbInt"><![CDATA[1]]></Field>
	<Field name="ICol" type="com.sunopsis.sql.DbInt"><![CDATA[1659]]></Field>
	<Field name="ISrcCol" type="com.sunopsis.sql.DbInt"><![CDATA[null]]></Field>
	<Field name="ITable" type="com.sunopsis.sql.DbInt"><![CDATA[192]]></Field>
	<Field name="ITxtColDesc" type="com.sunopsis.sql.DbInt"><![CDATA[null]]></Field>
	<Field name="LastDate" type="java.sql.Timestamp"><![CDATA[2021-05-21 12:32:43.0]]></Field>
	<Field name="LastUser" type="java.lang.String"><![CDATA[prueba]]></Field>
	<Field name="Longc" type="com.sunopsis.sql.DbInt"><![CDATA[4000]]></Field>
	<Field name="Pos" type="com.sunopsis.sql.DbInt"><![CDATA[3]]></Field>
	<Field name="RecCodeList" type="java.lang.String">null</Field>
	<Field name="Scalec" type="com.sunopsis.sql.DbInt"><![CDATA[null]]></Field>
	<Field name="ScdColType" type="java.lang.String">null</Field>
	<Field name="SourceDt" type="java.lang.String"><![CDATA[VARCHAR2]]></Field>
</Object>
<Object class="com.sunopsis.dwg.dbobj.SnpCol">
		<Field name="Bytes" type="com.sunopsis.sql.DbInt"><![CDATA[0]]></Field>
	<Field name="CheckFlow" type="java.lang.String"><![CDATA[1]]></Field>
	<Field name="CheckStat" type="java.lang.String"><![CDATA[0]]></Field>
	<Field name="ColDecSep" type="java.lang.String">null</Field>
	<Field name="ColFormat" type="java.lang.String">null</Field>
	<Field name="ColHeading" type="java.lang.String"><![CDATA[ID_DE_INTERVALO_DE_TIEMPO]]></Field>
	<Field name="ColMandatory" type="java.lang.String"><![CDATA[0]]></Field>
	<Field name="ColName" type="java.lang.String"><![CDATA[ID_DE_INTERVALO_DE_TIEMPO]]></Field>
	<Field name="ColNullIfErr" type="java.lang.String">null</Field>
	<Field name="DataFormat" type="java.lang.String">null</Field>
	<Field name="DefValue" type="java.lang.String">null</Field>
	<Field name="ExtVersion" type="java.lang.String">null</Field>
	<Field name="FilePos" type="com.sunopsis.sql.DbInt"><![CDATA[null]]></Field>
	<Field name="FirstDate" type="java.sql.Timestamp"><![CDATA[2021-05-21 12:32:43.0]]></Field>
	<Field name="FirstUser" type="java.lang.String"><![CDATA[prueba]]></Field>
	<Field name="GlobalId" type="java.lang.String"><![CDATA[c17ecd1e-b5bb-43e8-8e52-8fa7d78501bd]]></Field>
	<Field name="HbaseEncoding" type="java.lang.String">null</Field>
	<Field name="HiveSortbyPos" type="com.sunopsis.sql.DbInt"><![CDATA[null]]></Field>
	<Field name="IndChange" type="java.lang.String"><![CDATA[I]]></Field>
	<Field name="IndHiveCluster" type="java.lang.String">null</Field>
	<Field name="IndHivePartition" type="java.lang.String">null</Field>
	<Field name="IndHiveSort" type="java.lang.String">null</Field>
	<Field name="IndHiveSortbyAsc" type="java.lang.String">null</Field>
	<Field name="IndIn" type="java.lang.String">null</Field>
	<Field name="IndOut" type="java.lang.String">null</Field>
	<Field name="IndWrite" type="java.lang.String"><![CDATA[1]]></Field>
	<Field name="IndWsInsert" type="java.lang.String"><![CDATA[1]]></Field>
	<Field name="IndWsSelect" type="java.lang.String"><![CDATA[1]]></Field>
	<Field name="IndWsUpdate" type="java.lang.String"><![CDATA[1]]></Field>
	<Field name="IntVersion" type="com.sunopsis.sql.DbInt"><![CDATA[1]]></Field>
	<Field name="ICol" type="com.sunopsis.sql.DbInt"><![CDATA[1651]]></Field>
	<Field name="ISrcCol" type="com.sunopsis.sql.DbInt"><![CDATA[null]]></Field>
	<Field name="ITable" type="com.sunopsis.sql.DbInt"><![CDATA[192]]></Field>
	<Field name="ITxtColDesc" type="com.sunopsis.sql.DbInt"><![CDATA[null]]></Field>
	<Field name="LastDate" type="java.sql.Timestamp"><![CDATA[2021-05-21 12:32:43.0]]></Field>
	<Field name="LastUser" type="java.lang.String"><![CDATA[prueba]]></Field>
	<Field name="Longc" type="com.sunopsis.sql.DbInt"><![CDATA[4000]]></Field>
	<Field name="Pos" type="com.sunopsis.sql.DbInt"><![CDATA[4]]></Field>
	<Field name="RecCodeList" type="java.lang.String">null</Field>
	<Field name="Scalec" type="com.sunopsis.sql.DbInt"><![CDATA[null]]></Field>
	<Field name="ScdColType" type="java.lang.String">null</Field>
	<Field name="SourceDt" type="java.lang.String"><![CDATA[VARCHAR2]]></Field>
</Object>
<Object class="com.sunopsis.dwg.dbobj.SnpCol">
		<Field name="Bytes" type="com.sunopsis.sql.DbInt"><![CDATA[0]]></Field>
	<Field name="CheckFlow" type="java.lang.String"><![CDATA[1]]></Field>
	<Field name="CheckStat" type="java.lang.String"><![CDATA[0]]></Field>
	<Field name="ColDecSep" type="java.lang.String">null</Field>
	<Field name="ColFormat" type="java.lang.String">null</Field>
	<Field name="ColHeading" type="java.lang.String"><![CDATA[HORA_DE_RESERVA_DE_ACTIVIDAD]]></Field>
	<Field name="ColMandatory" type="java.lang.String"><![CDATA[0]]></Field>
	<Field name="ColName" type="java.lang.String"><![CDATA[HORA_DE_RESERVA_DE_ACTIVIDAD]]></Field>
	<Field name="ColNullIfErr" type="java.lang.String">null</Field>
	<Field name="DataFormat" type="java.lang.String">null</Field>
	<Field name="DefValue" type="java.lang.String">null</Field>
	<Field name="ExtVersion" type="java.lang.String">null</Field>
	<Field name="FilePos" type="com.sunopsis.sql.DbInt"><![CDATA[null]]></Field>
	<Field name="FirstDate" type="java.sql.Timestamp"><![CDATA[2021-05-21 12:32:42.0]]></Field>
	<Field name="FirstUser" type="java.lang.String"><![CDATA[prueba]]></Field>
	<Field name="GlobalId" type="java.lang.String"><![CDATA[b7daef79-43da-40cd-ae97-a1576e3c2834]]></Field>
	<Field name="HbaseEncoding" type="java.lang.String">null</Field>
	<Field name="HiveSortbyPos" type="com.sunopsis.sql.DbInt"><![CDATA[null]]></Field>
	<Field name="IndChange" type="java.lang.String"><![CDATA[I]]></Field>
	<Field name="IndHiveCluster" type="java.lang.String">null</Field>
	<Field name="IndHivePartition" type="java.lang.String">null</Field>
	<Field name="IndHiveSort" type="java.lang.String">null</Field>
	<Field name="IndHiveSortbyAsc" type="java.lang.String">null</Field>
	<Field name="IndIn" type="java.lang.String">null</Field>
	<Field name="IndOut" type="java.lang.String">null</Field>
	<Field name="IndWrite" type="java.lang.String"><![CDATA[1]]></Field>
	<Field name="IndWsInsert" type="java.lang.String"><![CDATA[1]]></Field>
	<Field name="IndWsSelect" type="java.lang.String"><![CDATA[1]]></Field>
	<Field name="IndWsUpdate" type="java.lang.String"><![CDATA[1]]></Field>
	<Field name="IntVersion" type="com.sunopsis.sql.DbInt"><![CDATA[1]]></Field>
	<Field name="ICol" type="com.sunopsis.sql.DbInt"><![CDATA[1648]]></Field>
	<Field name="ISrcCol" type="com.sunopsis.sql.DbInt"><![CDATA[null]]></Field>
	<Field name="ITable" type="com.sunopsis.sql.DbInt"><![CDATA[192]]></Field>
	<Field name="ITxtColDesc" type="com.sunopsis.sql.DbInt"><![CDATA[null]]></Field>
	<Field name="LastDate" type="java.sql.Timestamp"><![CDATA[2021-05-21 12:32:42.0]]></Field>
	<Field name="LastUser" type="java.lang.String"><![CDATA[prueba]]></Field>
	<Field name="Longc" type="com.sunopsis.sql.DbInt"><![CDATA[null]]></Field>
	<Field name="Pos" type="com.sunopsis.sql.DbInt"><![CDATA[5]]></Field>
	<Field name="RecCodeList" type="java.lang.String">null</Field>
	<Field name="Scalec" type="com.sunopsis.sql.DbInt"><![CDATA[null]]></Field>
	<Field name="ScdColType" type="java.lang.String">null</Field>
	<Field name="SourceDt" type="java.lang.String"><![CDATA[DATE]]></Field>
</Object>
<Object class="com.sunopsis.dwg.dbobj.SnpCol">
		<Field name="Bytes" type="com.sunopsis.sql.DbInt"><![CDATA[0]]></Field>
	<Field name="CheckFlow" type="java.lang.String"><![CDATA[1]]></Field>
	<Field name="CheckStat" type="java.lang.String"><![CDATA[0]]></Field>
	<Field name="ColDecSep" type="java.lang.String">null</Field>
	<Field name="ColFormat" type="java.lang.String">null</Field>
	<Field name="ColHeading" type="java.lang.String"><![CDATA[DURACIÓN]]></Field>
	<Field name="ColMandatory" type="java.lang.String"><![CDATA[0]]></Field>
	<Field name="ColName" type="java.lang.String"><![CDATA[DURACIÓN]]></Field>
	<Field name="ColNullIfErr" type="java.lang.String">null</Field>
	<Field name="DataFormat" type="java.lang.String">null</Field>
	<Field name="DefValue" type="java.lang.String">null</Field>
	<Field name="ExtVersion" type="java.lang.String">null</Field>
	<Field name="FilePos" type="com.sunopsis.sql.DbInt"><![CDATA[null]]></Field>
	<Field name="FirstDate" type="java.sql.Timestamp"><![CDATA[2021-05-21 12:32:42.0]]></Field>
	<Field name="FirstUser" type="java.lang.String"><![CDATA[prueba]]></Field>
	<Field name="GlobalId" type="java.lang.String"><![CDATA[b64fed1e-32df-4cff-a47b-16e0d1be91c3]]></Field>
	<Field name="HbaseEncoding" type="java.lang.String">null</Field>
	<Field name="HiveSortbyPos" type="com.sunopsis.sql.DbInt"><![CDATA[null]]></Field>
	<Field name="IndChange" type="java.lang.String"><![CDATA[I]]></Field>
	<Field name="IndHiveCluster" type="java.lang.String">null</Field>
	<Field name="IndHivePartition" type="java.lang.String">null</Field>
	<Field name="IndHiveSort" type="java.lang.String">null</Field>
	<Field name="IndHiveSortbyAsc" type="java.lang.String">null</Field>
	<Field name="IndIn" type="java.lang.String">null</Field>
	<Field name="IndOut" type="java.lang.String">null</Field>
	<Field name="IndWrite" type="java.lang.String"><![CDATA[1]]></Field>
	<Field name="IndWsInsert" type="java.lang.String"><![CDATA[1]]></Field>
	<Field name="IndWsSelect" type="java.lang.String"><![CDATA[1]]></Field>
	<Field name="IndWsUpdate" type="java.lang.String"><![CDATA[1]]></Field>
	<Field name="IntVersion" type="com.sunopsis.sql.DbInt"><![CDATA[1]]></Field>
	<Field name="ICol" type="com.sunopsis.sql.DbInt"><![CDATA[1642]]></Field>
	<Field name="ISrcCol" type="com.sunopsis.sql.DbInt"><![CDATA[null]]></Field>
	<Field name="ITable" type="com.sunopsis.sql.DbInt"><![CDATA[192]]></Field>
	<Field name="ITxtColDesc" type="com.sunopsis.sql.DbInt"><![CDATA[null]]></Field>
	<Field name="LastDate" type="java.sql.Timestamp"><![CDATA[2021-05-21 12:32:42.0]]></Field>
	<Field name="LastUser" type="java.lang.String"><![CDATA[prueba]]></Field>
	<Field name="Longc" type="com.sunopsis.sql.DbInt"><![CDATA[38]]></Field>
	<Field name="Pos" type="com.sunopsis.sql.DbInt"><![CDATA[6]]></Field>
	<Field name="RecCodeList" type="java.lang.String">null</Field>
	<Field name="Scalec" type="com.sunopsis.sql.DbInt"><![CDATA[0]]></Field>
	<Field name="ScdColType" type="java.lang.String">null</Field>
	<Field name="SourceDt" type="java.lang.String"><![CDATA[NUMBER]]></Field>
</Object>
<Object class="com.sunopsis.dwg.dbobj.SnpCol">
		<Field name="Bytes" type="com.sunopsis.sql.DbInt"><![CDATA[0]]></Field>
	<Field name="CheckFlow" type="java.lang.String"><![CDATA[1]]></Field>
	<Field name="CheckStat" type="java.lang.String"><![CDATA[0]]></Field>
	<Field name="ColDecSep" type="java.lang.String">null</Field>
	<Field name="ColFormat" type="java.lang.String">null</Field>
	<Field name="ColHeading" type="java.lang.String"><![CDATA[CÓDIGO_DE_CAUSA_1_DEL_IIMS]]></Field>
	<Field name="ColMandatory" type="java.lang.String"><![CDATA[0]]></Field>
	<Field name="ColName" type="java.lang.String"><![CDATA[CÓDIGO_DE_CAUSA_1_DEL_IIMS]]></Field>
	<Field name="ColNullIfErr" type="java.lang.String">null</Field>
	<Field name="DataFormat" type="java.lang.String">null</Field>
	<Field name="DefValue" type="java.lang.String">null</Field>
	<Field name="ExtVersion" type="java.lang.String">null</Field>
	<Field name="FilePos" type="com.sunopsis.sql.DbInt"><![CDATA[null]]></Field>
	<Field name="FirstDate" type="java.sql.Timestamp"><![CDATA[2021-05-21 12:32:42.0]]></Field>
	<Field name="FirstUser" type="java.lang.String"><![CDATA[prueba]]></Field>
	<Field name="GlobalId" type="java.lang.String"><![CDATA[ba417bd8-4a19-4d80-8cf6-d5d6a90774e4]]></Field>
	<Field name="HbaseEncoding" type="java.lang.String">null</Field>
	<Field name="HiveSortbyPos" type="com.sunopsis.sql.DbInt"><![CDATA[null]]></Field>
	<Field name="IndChange" type="java.lang.String"><![CDATA[I]]></Field>
	<Field name="IndHiveCluster" type="java.lang.String">null</Field>
	<Field name="IndHivePartition" type="java.lang.String">null</Field>
	<Field name="IndHiveSort" type="java.lang.String">null</Field>
	<Field name="IndHiveSortbyAsc" type="java.lang.String">null</Field>
	<Field name="IndIn" type="java.lang.String">null</Field>
	<Field name="IndOut" type="java.lang.String">null</Field>
	<Field name="IndWrite" type="java.lang.String"><![CDATA[1]]></Field>
	<Field name="IndWsInsert" type="java.lang.String"><![CDATA[1]]></Field>
	<Field name="IndWsSelect" type="java.lang.String"><![CDATA[1]]></Field>
	<Field name="IndWsUpdate" type="java.lang.String"><![CDATA[1]]></Field>
	<Field name="IntVersion" type="com.sunopsis.sql.DbInt"><![CDATA[1]]></Field>
	<Field name="ICol" type="com.sunopsis.sql.DbInt"><![CDATA[1639]]></Field>
	<Field name="ISrcCol" type="com.sunopsis.sql.DbInt"><![CDATA[null]]></Field>
	<Field name="ITable" type="com.sunopsis.sql.DbInt"><![CDATA[192]]></Field>
	<Field name="ITxtColDesc" type="com.sunopsis.sql.DbInt"><![CDATA[null]]></Field>
	<Field name="LastDate" type="java.sql.Timestamp"><![CDATA[2021-05-21 12:32:42.0]]></Field>
	<Field name="LastUser" type="java.lang.String"><![CDATA[prueba]]></Field>
	<Field name="Longc" type="com.sunopsis.sql.DbInt"><![CDATA[4000]]></Field>
	<Field name="Pos" type="com.sunopsis.sql.DbInt"><![CDATA[7]]></Field>
	<Field name="RecCodeList" type="java.lang.String">null</Field>
	<Field name="Scalec" type="com.sunopsis.sql.DbInt"><![CDATA[null]]></Field>
	<Field name="ScdColType" type="java.lang.String">null</Field>
	<Field name="SourceDt" type="java.lang.String"><![CDATA[VARCHAR2]]></Field>
</Object>
<Object class="com.sunopsis.dwg.dbobj.SnpCol">
		<Field name="Bytes" type="com.sunopsis.sql.DbInt"><![CDATA[0]]></Field>
	<Field name="CheckFlow" type="java.lang.String"><![CDATA[1]]></Field>
	<Field name="CheckStat" type="java.lang.String"><![CDATA[0]]></Field>
	<Field name="ColDecSep" type="java.lang.String">null</Field>
	<Field name="ColFormat" type="java.lang.String">null</Field>
	<Field name="ColHeading" type="java.lang.String"><![CDATA[CÓDIGO_DE_CAUSA_2_DEL_IIMS]]></Field>
	<Field name="ColMandatory" type="java.lang.String"><![CDATA[0]]></Field>
	<Field name="ColName" type="java.lang.String"><![CDATA[CÓDIGO_DE_CAUSA_2_DEL_IIMS]]></Field>
	<Field name="ColNullIfErr" type="java.lang.String">null</Field>
	<Field name="DataFormat" type="java.lang.String">null</Field>
	<Field name="DefValue" type="java.lang.String">null</Field>
	<Field name="ExtVersion" type="java.lang.String">null</Field>
	<Field name="FilePos" type="com.sunopsis.sql.DbInt"><![CDATA[null]]></Field>
	<Field name="FirstDate" type="java.sql.Timestamp"><![CDATA[2021-05-21 12:32:42.0]]></Field>
	<Field name="FirstUser" type="java.lang.String"><![CDATA[prueba]]></Field>
	<Field name="GlobalId" type="java.lang.String"><![CDATA[3b954dc2-ca68-4b99-88c0-55904f8d4821]]></Field>
	<Field name="HbaseEncoding" type="java.lang.String">null</Field>
	<Field name="HiveSortbyPos" type="com.sunopsis.sql.DbInt"><![CDATA[null]]></Field>
	<Field name="IndChange" type="java.lang.String"><![CDATA[I]]></Field>
	<Field name="IndHiveCluster" type="java.lang.String">null</Field>
	<Field name="IndHivePartition" type="java.lang.String">null</Field>
	<Field name="IndHiveSort" type="java.lang.String">null</Field>
	<Field name="IndHiveSortbyAsc" type="java.lang.String">null</Field>
	<Field name="IndIn" type="java.lang.String">null</Field>
	<Field name="IndOut" type="java.lang.String">null</Field>
	<Field name="IndWrite" type="java.lang.String"><![CDATA[1]]></Field>
	<Field name="IndWsInsert" type="java.lang.String"><![CDATA[1]]></Field>
	<Field name="IndWsSelect" type="java.lang.String"><![CDATA[1]]></Field>
	<Field name="IndWsUpdate" type="java.lang.String"><![CDATA[1]]></Field>
	<Field name="IntVersion" type="com.sunopsis.sql.DbInt"><![CDATA[1]]></Field>
	<Field name="ICol" type="com.sunopsis.sql.DbInt"><![CDATA[1640]]></Field>
	<Field name="ISrcCol" type="com.sunopsis.sql.DbInt"><![CDATA[null]]></Field>
	<Field name="ITable" type="com.sunopsis.sql.DbInt"><![CDATA[192]]></Field>
	<Field name="ITxtColDesc" type="com.sunopsis.sql.DbInt"><![CDATA[null]]></Field>
	<Field name="LastDate" type="java.sql.Timestamp"><![CDATA[2021-05-21 12:32:42.0]]></Field>
	<Field name="LastUser" type="java.lang.String"><![CDATA[prueba]]></Field>
	<Field name="Longc" type="com.sunopsis.sql.DbInt"><![CDATA[4000]]></Field>
	<Field name="Pos" type="com.sunopsis.sql.DbInt"><![CDATA[8]]></Field>
	<Field name="RecCodeList" type="java.lang.String">null</Field>
	<Field name="Scalec" type="com.sunopsis.sql.DbInt"><![CDATA[null]]></Field>
	<Field name="ScdColType" type="java.lang.String">null</Field>
	<Field name="SourceDt" type="java.lang.String"><![CDATA[VARCHAR2]]></Field>
</Object>
<Object class="com.sunopsis.dwg.dbobj.SnpCol">
		<Field name="Bytes" type="com.sunopsis.sql.DbInt"><![CDATA[0]]></Field>
	<Field name="CheckFlow" type="java.lang.String"><![CDATA[1]]></Field>
	<Field name="CheckStat" type="java.lang.String"><![CDATA[0]]></Field>
	<Field name="ColDecSep" type="java.lang.String">null</Field>
	<Field name="ColFormat" type="java.lang.String">null</Field>
	<Field name="ColHeading" type="java.lang.String"><![CDATA[CÓDIGO_DE_CAUSA_3_DEL_IIMS]]></Field>
	<Field name="ColMandatory" type="java.lang.String"><![CDATA[0]]></Field>
	<Field name="ColName" type="java.lang.String"><![CDATA[CÓDIGO_DE_CAUSA_3_DEL_IIMS]]></Field>
	<Field name="ColNullIfErr" type="java.lang.String">null</Field>
	<Field name="DataFormat" type="java.lang.String">null</Field>
	<Field name="DefValue" type="java.lang.String">null</Field>
	<Field name="ExtVersion" type="java.lang.String">null</Field>
	<Field name="FilePos" type="com.sunopsis.sql.DbInt"><![CDATA[null]]></Field>
	<Field name="FirstDate" type="java.sql.Timestamp"><![CDATA[2021-05-21 12:32:42.0]]></Field>
	<Field name="FirstUser" type="java.lang.String"><![CDATA[prueba]]></Field>
	<Field name="GlobalId" type="java.lang.String"><![CDATA[b9ac1cce-8c65-4e4f-9688-adb05d4b5a62]]></Field>
	<Field name="HbaseEncoding" type="java.lang.String">null</Field>
	<Field name="HiveSortbyPos" type="com.sunopsis.sql.DbInt"><![CDATA[null]]></Field>
	<Field name="IndChange" type="java.lang.String"><![CDATA[I]]></Field>
	<Field name="IndHiveCluster" type="java.lang.String">null</Field>
	<Field name="IndHivePartition" type="java.lang.String">null</Field>
	<Field name="IndHiveSort" type="java.lang.String">null</Field>
	<Field name="IndHiveSortbyAsc" type="java.lang.String">null</Field>
	<Field name="IndIn" type="java.lang.String">null</Field>
	<Field name="IndOut" type="java.lang.String">null</Field>
	<Field name="IndWrite" type="java.lang.String"><![CDATA[1]]></Field>
	<Field name="IndWsInsert" type="java.lang.String"><![CDATA[1]]></Field>
	<Field name="IndWsSelect" type="java.lang.String"><![CDATA[1]]></Field>
	<Field name="IndWsUpdate" type="java.lang.String"><![CDATA[1]]></Field>
	<Field name="IntVersion" type="com.sunopsis.sql.DbInt"><![CDATA[1]]></Field>
	<Field name="ICol" type="com.sunopsis.sql.DbInt"><![CDATA[1641]]></Field>
	<Field name="ISrcCol" type="com.sunopsis.sql.DbInt"><![CDATA[null]]></Field>
	<Field name="ITable" type="com.sunopsis.sql.DbInt"><![CDATA[192]]></Field>
	<Field name="ITxtColDesc" type="com.sunopsis.sql.DbInt"><![CDATA[null]]></Field>
	<Field name="LastDate" type="java.sql.Timestamp"><![CDATA[2021-05-21 12:32:42.0]]></Field>
	<Field name="LastUser" type="java.lang.String"><![CDATA[prueba]]></Field>
	<Field name="Longc" type="com.sunopsis.sql.DbInt"><![CDATA[4000]]></Field>
	<Field name="Pos" type="com.sunopsis.sql.DbInt"><![CDATA[9]]></Field>
	<Field name="RecCodeList" type="java.lang.String">null</Field>
	<Field name="Scalec" type="com.sunopsis.sql.DbInt"><![CDATA[null]]></Field>
	<Field name="ScdColType" type="java.lang.String">null</Field>
	<Field name="SourceDt" type="java.lang.String"><![CDATA[VARCHAR2]]></Field>
</Object>
<Object class="com.sunopsis.dwg.dbobj.SnpCol">
		<Field name="Bytes" type="com.sunopsis.sql.DbInt"><![CDATA[0]]></Field>
	<Field name="CheckFlow" type="java.lang.String"><![CDATA[1]]></Field>
	<Field name="CheckStat" type="java.lang.String"><![CDATA[0]]></Field>
	<Field name="ColDecSep" type="java.lang.String">null</Field>
	<Field name="ColFormat" type="java.lang.String">null</Field>
	<Field name="ColHeading" type="java.lang.String"><![CDATA[ESTADO_DE_ACTIVIDAD]]></Field>
	<Field name="ColMandatory" type="java.lang.String"><![CDATA[0]]></Field>
	<Field name="ColName" type="java.lang.String"><![CDATA[ESTADO_DE_ACTIVIDAD]]></Field>
	<Field name="ColNullIfErr" type="java.lang.String">null</Field>
	<Field name="DataFormat" type="java.lang.String">null</Field>
	<Field name="DefValue" type="java.lang.String">null</Field>
	<Field name="ExtVersion" type="java.lang.String">null</Field>
	<Field name="FilePos" type="com.sunopsis.sql.DbInt"><![CDATA[null]]></Field>
	<Field name="FirstDate" type="java.sql.Timestamp"><![CDATA[2021-05-21 12:32:42.0]]></Field>
	<Field name="FirstUser" type="java.lang.String"><![CDATA[prueba]]></Field>
	<Field name="GlobalId" type="java.lang.String"><![CDATA[a37e97ca-581f-4194-8444-cb1acbdf95bb]]></Field>
	<Field name="HbaseEncoding" type="java.lang.String">null</Field>
	<Field name="HiveSortbyPos" type="com.sunopsis.sql.DbInt"><![CDATA[null]]></Field>
	<Field name="IndChange" type="java.lang.String"><![CDATA[I]]></Field>
	<Field name="IndHiveCluster" type="java.lang.String">null</Field>
	<Field name="IndHivePartition" type="java.lang.String">null</Field>
	<Field name="IndHiveSort" type="java.lang.String">null</Field>
	<Field name="IndHiveSortbyAsc" type="java.lang.String">null</Field>
	<Field name="IndIn" type="java.lang.String">null</Field>
	<Field name="IndOut" type="java.lang.String">null</Field>
	<Field name="IndWrite" type="java.lang.String"><![CDATA[1]]></Field>
	<Field name="IndWsInsert" type="java.lang.String"><![CDATA[1]]></Field>
	<Field name="IndWsSelect" type="java.lang.String"><![CDATA[1]]></Field>
	<Field name="IndWsUpdate" type="java.lang.String"><![CDATA[1]]></Field>
	<Field name="IntVersion" type="com.sunopsis.sql.DbInt"><![CDATA[1]]></Field>
	<Field name="ICol" type="com.sunopsis.sql.DbInt"><![CDATA[1643]]></Field>
	<Field name="ISrcCol" type="com.sunopsis.sql.DbInt"><![CDATA[null]]></Field>
	<Field name="ITable" type="com.sunopsis.sql.DbInt"><![CDATA[192]]></Field>
	<Field name="ITxtColDesc" type="com.sunopsis.sql.DbInt"><![CDATA[null]]></Field>
	<Field name="LastDate" type="java.sql.Timestamp"><![CDATA[2021-05-21 12:32:42.0]]></Field>
	<Field name="LastUser" type="java.lang.String"><![CDATA[prueba]]></Field>
	<Field name="Longc" type="com.sunopsis.sql.DbInt"><![CDATA[4000]]></Field>
	<Field name="Pos" type="com.sunopsis.sql.DbInt"><![CDATA[10]]></Field>
	<Field name="RecCodeList" type="java.lang.String">null</Field>
	<Field name="Scalec" type="com.sunopsis.sql.DbInt"><![CDATA[null]]></Field>
	<Field name="ScdColType" type="java.lang.String">null</Field>
	<Field name="SourceDt" type="java.lang.String"><![CDATA[VARCHAR2]]></Field>
</Object>
<Object class="com.sunopsis.dwg.dbobj.SnpCol">
		<Field name="Bytes" type="com.sunopsis.sql.DbInt"><![CDATA[0]]></Field>
	<Field name="CheckFlow" type="java.lang.String"><![CDATA[1]]></Field>
	<Field name="CheckStat" type="java.lang.String"><![CDATA[0]]></Field>
	<Field name="ColDecSep" type="java.lang.String">null</Field>
	<Field name="ColFormat" type="java.lang.String">null</Field>
	<Field name="ColHeading" type="java.lang.String"><![CDATA[CAUSAS_DE_NO_REALIZADO]]></Field>
	<Field name="ColMandatory" type="java.lang.String"><![CDATA[0]]></Field>
	<Field name="ColName" type="java.lang.String"><![CDATA[CAUSAS_DE_NO_REALIZADO]]></Field>
	<Field name="ColNullIfErr" type="java.lang.String">null</Field>
	<Field name="DataFormat" type="java.lang.String">null</Field>
	<Field name="DefValue" type="java.lang.String">null</Field>
	<Field name="ExtVersion" type="java.lang.String">null</Field>
	<Field name="FilePos" type="com.sunopsis.sql.DbInt"><![CDATA[null]]></Field>
	<Field name="FirstDate" type="java.sql.Timestamp"><![CDATA[2021-05-21 12:32:42.0]]></Field>
	<Field name="FirstUser" type="java.lang.String"><![CDATA[prueba]]></Field>
	<Field name="GlobalId" type="java.lang.String"><![CDATA[c96540cb-90e0-41c4-8600-a6230158debb]]></Field>
	<Field name="HbaseEncoding" type="java.lang.String">null</Field>
	<Field name="HiveSortbyPos" type="com.sunopsis.sql.DbInt"><![CDATA[null]]></Field>
	<Field name="IndChange" type="java.lang.String"><![CDATA[I]]></Field>
	<Field name="IndHiveCluster" type="java.lang.String">null</Field>
	<Field name="IndHivePartition" type="java.lang.String">null</Field>
	<Field name="IndHiveSort" type="java.lang.String">null</Field>
	<Field name="IndHiveSortbyAsc" type="java.lang.String">null</Field>
	<Field name="IndIn" type="java.lang.String">null</Field>
	<Field name="IndOut" type="java.lang.String">null</Field>
	<Field name="IndWrite" type="java.lang.String"><![CDATA[1]]></Field>
	<Field name="IndWsInsert" type="java.lang.String"><![CDATA[1]]></Field>
	<Field name="IndWsSelect" type="java.lang.String"><![CDATA[1]]></Field>
	<Field name="IndWsUpdate" type="java.lang.String"><![CDATA[1]]></Field>
	<Field name="IntVersion" type="com.sunopsis.sql.DbInt"><![CDATA[1]]></Field>
	<Field name="ICol" type="com.sunopsis.sql.DbInt"><![CDATA[1638]]></Field>
	<Field name="ISrcCol" type="com.sunopsis.sql.DbInt"><![CDATA[null]]></Field>
	<Field name="ITable" type="com.sunopsis.sql.DbInt"><![CDATA[192]]></Field>
	<Field name="ITxtColDesc" type="com.sunopsis.sql.DbInt"><![CDATA[null]]></Field>
	<Field name="LastDate" type="java.sql.Timestamp"><![CDATA[2021-05-21 12:32:42.0]]></Field>
	<Field name="LastUser" type="java.lang.String"><![CDATA[prueba]]></Field>
	<Field name="Longc" type="com.sunopsis.sql.DbInt"><![CDATA[4000]]></Field>
	<Field name="Pos" type="com.sunopsis.sql.DbInt"><![CDATA[11]]></Field>
	<Field name="RecCodeList" type="java.lang.String">null</Field>
	<Field name="Scalec" type="com.sunopsis.sql.DbInt"><![CDATA[null]]></Field>
	<Field name="ScdColType" type="java.lang.String">null</Field>
	<Field name="SourceDt" type="java.lang.String"><![CDATA[VARCHAR2]]></Field>
</Object>
<Object class="com.sunopsis.dwg.dbobj.SnpCol">
		<Field name="Bytes" type="com.sunopsis.sql.DbInt"><![CDATA[0]]></Field>
	<Field name="CheckFlow" type="java.lang.String"><![CDATA[1]]></Field>
	<Field name="CheckStat" type="java.lang.String"><![CDATA[0]]></Field>
	<Field name="ColDecSep" type="java.lang.String">null</Field>
	<Field name="ColFormat" type="java.lang.String">null</Field>
	<Field name="ColHeading" type="java.lang.String"><![CDATA[ID_ALIADO]]></Field>
	<Field name="ColMandatory" type="java.lang.String"><![CDATA[0]]></Field>
	<Field name="ColName" type="java.lang.String"><![CDATA[ID_ALIADO]]></Field>
	<Field name="ColNullIfErr" type="java.lang.String">null</Field>
	<Field name="DataFormat" type="java.lang.String">null</Field>
	<Field name="DefValue" type="java.lang.String">null</Field>
	<Field name="ExtVersion" type="java.lang.String">null</Field>
	<Field name="FilePos" type="com.sunopsis.sql.DbInt"><![CDATA[null]]></Field>
	<Field name="FirstDate" type="java.sql.Timestamp"><![CDATA[2021-05-21 12:32:42.0]]></Field>
	<Field name="FirstUser" type="java.lang.String"><![CDATA[prueba]]></Field>
	<Field name="GlobalId" type="java.lang.String"><![CDATA[2ee44a0b-8a10-44d7-8230-e9d724d6b10a]]></Field>
	<Field name="HbaseEncoding" type="java.lang.String">null</Field>
	<Field name="HiveSortbyPos" type="com.sunopsis.sql.DbInt"><![CDATA[null]]></Field>
	<Field name="IndChange" type="java.lang.String"><![CDATA[I]]></Field>
	<Field name="IndHiveCluster" type="java.lang.String">null</Field>
	<Field name="IndHivePartition" type="java.lang.String">null</Field>
	<Field name="IndHiveSort" type="java.lang.String">null</Field>
	<Field name="IndHiveSortbyAsc" type="java.lang.String">null</Field>
	<Field name="IndIn" type="java.lang.String">null</Field>
	<Field name="IndOut" type="java.lang.String">null</Field>
	<Field name="IndWrite" type="java.lang.String"><![CDATA[1]]></Field>
	<Field name="IndWsInsert" type="java.lang.String"><![CDATA[1]]></Field>
	<Field name="IndWsSelect" type="java.lang.String"><![CDATA[1]]></Field>
	<Field name="IndWsUpdate" type="java.lang.String"><![CDATA[1]]></Field>
	<Field name="IntVersion" type="com.sunopsis.sql.DbInt"><![CDATA[1]]></Field>
	<Field name="ICol" type="com.sunopsis.sql.DbInt"><![CDATA[1649]]></Field>
	<Field name="ISrcCol" type="com.sunopsis.sql.DbInt"><![CDATA[null]]></Field>
	<Field name="ITable" type="com.sunopsis.sql.DbInt"><![CDATA[192]]></Field>
	<Field name="ITxtColDesc" type="com.sunopsis.sql.DbInt"><![CDATA[null]]></Field>
	<Field name="LastDate" type="java.sql.Timestamp"><![CDATA[2021-05-21 12:32:42.0]]></Field>
	<Field name="LastUser" type="java.lang.String"><![CDATA[prueba]]></Field>
	<Field name="Longc" type="com.sunopsis.sql.DbInt"><![CDATA[4000]]></Field>
	<Field name="Pos" type="com.sunopsis.sql.DbInt"><![CDATA[12]]></Field>
	<Field name="RecCodeList" type="java.lang.String">null</Field>
	<Field name="Scalec" type="com.sunopsis.sql.DbInt"><![CDATA[null]]></Field>
	<Field name="ScdColType" type="java.lang.String">null</Field>
	<Field name="SourceDt" type="java.lang.String"><![CDATA[VARCHAR2]]></Field>
</Object>
<Object class="com.sunopsis.dwg.dbobj.SnpCol">
		<Field name="Bytes" type="com.sunopsis.sql.DbInt"><![CDATA[0]]></Field>
	<Field name="CheckFlow" type="java.lang.String"><![CDATA[1]]></Field>
	<Field name="CheckStat" type="java.lang.String"><![CDATA[0]]></Field>
	<Field name="ColDecSep" type="java.lang.String">null</Field>
	<Field name="ColFormat" type="java.lang.String">null</Field>
	<Field name="ColHeading" type="java.lang.String"><![CDATA[ID_EXTERNO_DE_RECURSO]]></Field>
	<Field name="ColMandatory" type="java.lang.String"><![CDATA[0]]></Field>
	<Field name="ColName" type="java.lang.String"><![CDATA[ID_EXTERNO_DE_RECURSO]]></Field>
	<Field name="ColNullIfErr" type="java.lang.String">null</Field>
	<Field name="DataFormat" type="java.lang.String">null</Field>
	<Field name="DefValue" type="java.lang.String">null</Field>
	<Field name="ExtVersion" type="java.lang.String">null</Field>
	<Field name="FilePos" type="com.sunopsis.sql.DbInt"><![CDATA[null]]></Field>
	<Field name="FirstDate" type="java.sql.Timestamp"><![CDATA[2021-05-21 12:32:43.0]]></Field>
	<Field name="FirstUser" type="java.lang.String"><![CDATA[prueba]]></Field>
	<Field name="GlobalId" type="java.lang.String"><![CDATA[66600c9f-dd80-4a69-b238-67d8bdda21ea]]></Field>
	<Field name="HbaseEncoding" type="java.lang.String">null</Field>
	<Field name="HiveSortbyPos" type="com.sunopsis.sql.DbInt"><![CDATA[null]]></Field>
	<Field name="IndChange" type="java.lang.String"><![CDATA[I]]></Field>
	<Field name="IndHiveCluster" type="java.lang.String">null</Field>
	<Field name="IndHivePartition" type="java.lang.String">null</Field>
	<Field name="IndHiveSort" type="java.lang.String">null</Field>
	<Field name="IndHiveSortbyAsc" type="java.lang.String">null</Field>
	<Field name="IndIn" type="java.lang.String">null</Field>
	<Field name="IndOut" type="java.lang.String">null</Field>
	<Field name="IndWrite" type="java.lang.String"><![CDATA[1]]></Field>
	<Field name="IndWsInsert" type="java.lang.String"><![CDATA[1]]></Field>
	<Field name="IndWsSelect" type="java.lang.String"><![CDATA[1]]></Field>
	<Field name="IndWsUpdate" type="java.lang.String"><![CDATA[1]]></Field>
	<Field name="IntVersion" type="com.sunopsis.sql.DbInt"><![CDATA[1]]></Field>
	<Field name="ICol" type="com.sunopsis.sql.DbInt"><![CDATA[1652]]></Field>
	<Field name="ISrcCol" type="com.sunopsis.sql.DbInt"><![CDATA[null]]></Field>
	<Field name="ITable" type="com.sunopsis.sql.DbInt"><![CDATA[192]]></Field>
	<Field name="ITxtColDesc" type="com.sunopsis.sql.DbInt"><![CDATA[null]]></Field>
	<Field name="LastDate" type="java.sql.Timestamp"><![CDATA[2021-05-21 12:32:43.0]]></Field>
	<Field name="LastUser" type="java.lang.String"><![CDATA[prueba]]></Field>
	<Field name="Longc" type="com.sunopsis.sql.DbInt"><![CDATA[4000]]></Field>
	<Field name="Pos" type="com.sunopsis.sql.DbInt"><![CDATA[13]]></Field>
	<Field name="RecCodeList" type="java.lang.String">null</Field>
	<Field name="Scalec" type="com.sunopsis.sql.DbInt"><![CDATA[null]]></Field>
	<Field name="ScdColType" type="java.lang.String">null</Field>
	<Field name="SourceDt" type="java.lang.String"><![CDATA[VARCHAR2]]></Field>
</Object>
<Object class="com.sunopsis.dwg.dbobj.SnpCol">
		<Field name="Bytes" type="com.sunopsis.sql.DbInt"><![CDATA[0]]></Field>
	<Field name="CheckFlow" type="java.lang.String"><![CDATA[1]]></Field>
	<Field name="CheckStat" type="java.lang.String"><![CDATA[0]]></Field>
	<Field name="ColDecSep" type="java.lang.String">null</Field>
	<Field name="ColFormat" type="java.lang.String">null</Field>
	<Field name="ColHeading" type="java.lang.String"><![CDATA[NÚMERO_DE_CUENTA]]></Field>
	<Field name="ColMandatory" type="java.lang.String"><![CDATA[0]]></Field>
	<Field name="ColName" type="java.lang.String"><![CDATA[NÚMERO_DE_CUENTA]]></Field>
	<Field name="ColNullIfErr" type="java.lang.String">null</Field>
	<Field name="DataFormat" type="java.lang.String">null</Field>
	<Field name="DefValue" type="java.lang.String">null</Field>
	<Field name="ExtVersion" type="java.lang.String">null</Field>
	<Field name="FilePos" type="com.sunopsis.sql.DbInt"><![CDATA[null]]></Field>
	<Field name="FirstDate" type="java.sql.Timestamp"><![CDATA[2021-05-21 12:32:43.0]]></Field>
	<Field name="FirstUser" type="java.lang.String"><![CDATA[prueba]]></Field>
	<Field name="GlobalId" type="java.lang.String"><![CDATA[46ad6eea-3ee4-4619-a681-c5169f863965]]></Field>
	<Field name="HbaseEncoding" type="java.lang.String">null</Field>
	<Field name="HiveSortbyPos" type="com.sunopsis.sql.DbInt"><![CDATA[null]]></Field>
	<Field name="IndChange" type="java.lang.String"><![CDATA[I]]></Field>
	<Field name="IndHiveCluster" type="java.lang.String">null</Field>
	<Field name="IndHivePartition" type="java.lang.String">null</Field>
	<Field name="IndHiveSort" type="java.lang.String">null</Field>
	<Field name="IndHiveSortbyAsc" type="java.lang.String">null</Field>
	<Field name="IndIn" type="java.lang.String">null</Field>
	<Field name="IndOut" type="java.lang.String">null</Field>
	<Field name="IndWrite" type="java.lang.String"><![CDATA[1]]></Field>
	<Field name="IndWsInsert" type="java.lang.String"><![CDATA[1]]></Field>
	<Field name="IndWsSelect" type="java.lang.String"><![CDATA[1]]></Field>
	<Field name="IndWsUpdate" type="java.lang.String"><![CDATA[1]]></Field>
	<Field name="IntVersion" type="com.sunopsis.sql.DbInt"><![CDATA[1]]></Field>
	<Field name="ICol" type="com.sunopsis.sql.DbInt"><![CDATA[1655]]></Field>
	<Field name="ISrcCol" type="com.sunopsis.sql.DbInt"><![CDATA[null]]></Field>
	<Field name="ITable" type="com.sunopsis.sql.DbInt"><![CDATA[192]]></Field>
	<Field name="ITxtColDesc" type="com.sunopsis.sql.DbInt"><![CDATA[null]]></Field>
	<Field name="LastDate" type="java.sql.Timestamp"><![CDATA[2021-05-21 12:32:43.0]]></Field>
	<Field name="LastUser" type="java.lang.String"><![CDATA[prueba]]></Field>
	<Field name="Longc" type="com.sunopsis.sql.DbInt"><![CDATA[4000]]></Field>
	<Field name="Pos" type="com.sunopsis.sql.DbInt"><![CDATA[14]]></Field>
	<Field name="RecCodeList" type="java.lang.String">null</Field>
	<Field name="Scalec" type="com.sunopsis.sql.DbInt"><![CDATA[null]]></Field>
	<Field name="ScdColType" type="java.lang.String">null</Field>
	<Field name="SourceDt" type="java.lang.String"><![CDATA[VARCHAR2]]></Field>
</Object>
<Object class="com.sunopsis.dwg.dbobj.SnpCol">
		<Field name="Bytes" type="com.sunopsis.sql.DbInt"><![CDATA[0]]></Field>
	<Field name="CheckFlow" type="java.lang.String"><![CDATA[1]]></Field>
	<Field name="CheckStat" type="java.lang.String"><![CDATA[0]]></Field>
	<Field name="ColDecSep" type="java.lang.String">null</Field>
	<Field name="ColFormat" type="java.lang.String">null</Field>
	<Field name="ColHeading" type="java.lang.String"><![CDATA[INICIO_DE_VENTANA_DE_ENTREGA]]></Field>
	<Field name="ColMandatory" type="java.lang.String"><![CDATA[0]]></Field>
	<Field name="ColName" type="java.lang.String"><![CDATA[INICIO_DE_VENTANA_DE_ENTREGA]]></Field>
	<Field name="ColNullIfErr" type="java.lang.String">null</Field>
	<Field name="DataFormat" type="java.lang.String">null</Field>
	<Field name="DefValue" type="java.lang.String">null</Field>
	<Field name="ExtVersion" type="java.lang.String">null</Field>
	<Field name="FilePos" type="com.sunopsis.sql.DbInt"><![CDATA[null]]></Field>
	<Field name="FirstDate" type="java.sql.Timestamp"><![CDATA[2021-05-21 12:32:43.0]]></Field>
	<Field name="FirstUser" type="java.lang.String"><![CDATA[prueba]]></Field>
	<Field name="GlobalId" type="java.lang.String"><![CDATA[87571aa7-f35f-4fa9-9227-27f6b30a739c]]></Field>
	<Field name="HbaseEncoding" type="java.lang.String">null</Field>
	<Field name="HiveSortbyPos" type="com.sunopsis.sql.DbInt"><![CDATA[null]]></Field>
	<Field name="IndChange" type="java.lang.String"><![CDATA[I]]></Field>
	<Field name="IndHiveCluster" type="java.lang.String">null</Field>
	<Field name="IndHivePartition" type="java.lang.String">null</Field>
	<Field name="IndHiveSort" type="java.lang.String">null</Field>
	<Field name="IndHiveSortbyAsc" type="java.lang.String">null</Field>
	<Field name="IndIn" type="java.lang.String">null</Field>
	<Field name="IndOut" type="java.lang.String">null</Field>
	<Field name="IndWrite" type="java.lang.String"><![CDATA[1]]></Field>
	<Field name="IndWsInsert" type="java.lang.String"><![CDATA[1]]></Field>
	<Field name="IndWsSelect" type="java.lang.String"><![CDATA[1]]></Field>
	<Field name="IndWsUpdate" type="java.lang.String"><![CDATA[1]]></Field>
	<Field name="IntVersion" type="com.sunopsis.sql.DbInt"><![CDATA[1]]></Field>
	<Field name="ICol" type="com.sunopsis.sql.DbInt"><![CDATA[1653]]></Field>
	<Field name="ISrcCol" type="com.sunopsis.sql.DbInt"><![CDATA[null]]></Field>
	<Field name="ITable" type="com.sunopsis.sql.DbInt"><![CDATA[192]]></Field>
	<Field name="ITxtColDesc" type="com.sunopsis.sql.DbInt"><![CDATA[null]]></Field>
	<Field name="LastDate" type="java.sql.Timestamp"><![CDATA[2021-05-21 12:32:43.0]]></Field>
	<Field name="LastUser" type="java.lang.String"><![CDATA[prueba]]></Field>
	<Field name="Longc" type="com.sunopsis.sql.DbInt"><![CDATA[null]]></Field>
	<Field name="Pos" type="com.sunopsis.sql.DbInt"><![CDATA[15]]></Field>
	<Field name="RecCodeList" type="java.lang.String">null</Field>
	<Field name="Scalec" type="com.sunopsis.sql.DbInt"><![CDATA[null]]></Field>
	<Field name="ScdColType" type="java.lang.String">null</Field>
	<Field name="SourceDt" type="java.lang.String"><![CDATA[DATE]]></Field>
</Object>
<Object class="com.sunopsis.dwg.dbobj.SnpCol">
		<Field name="Bytes" type="com.sunopsis.sql.DbInt"><![CDATA[0]]></Field>
	<Field name="CheckFlow" type="java.lang.String"><![CDATA[1]]></Field>
	<Field name="CheckStat" type="java.lang.String"><![CDATA[0]]></Field>
	<Field name="ColDecSep" type="java.lang.String">null</Field>
	<Field name="ColFormat" type="java.lang.String">null</Field>
	<Field name="ColHeading" type="java.lang.String"><![CDATA[FINALIZACIÓN_DE_VENTANA_DE_E]]></Field>
	<Field name="ColMandatory" type="java.lang.String"><![CDATA[0]]></Field>
	<Field name="ColName" type="java.lang.String"><![CDATA[FINALIZACIÓN_DE_VENTANA_DE_E]]></Field>
	<Field name="ColNullIfErr" type="java.lang.String">null</Field>
	<Field name="DataFormat" type="java.lang.String">null</Field>
	<Field name="DefValue" type="java.lang.String">null</Field>
	<Field name="ExtVersion" type="java.lang.String">null</Field>
	<Field name="FilePos" type="com.sunopsis.sql.DbInt"><![CDATA[null]]></Field>
	<Field name="FirstDate" type="java.sql.Timestamp"><![CDATA[2021-05-21 12:32:42.0]]></Field>
	<Field name="FirstUser" type="java.lang.String"><![CDATA[prueba]]></Field>
	<Field name="GlobalId" type="java.lang.String"><![CDATA[adfc0c4a-a1b0-459a-a2a1-564773ace9e5]]></Field>
	<Field name="HbaseEncoding" type="java.lang.String">null</Field>
	<Field name="HiveSortbyPos" type="com.sunopsis.sql.DbInt"><![CDATA[null]]></Field>
	<Field name="IndChange" type="java.lang.String"><![CDATA[I]]></Field>
	<Field name="IndHiveCluster" type="java.lang.String">null</Field>
	<Field name="IndHivePartition" type="java.lang.String">null</Field>
	<Field name="IndHiveSort" type="java.lang.String">null</Field>
	<Field name="IndHiveSortbyAsc" type="java.lang.String">null</Field>
	<Field name="IndIn" type="java.lang.String">null</Field>
	<Field name="IndOut" type="java.lang.String">null</Field>
	<Field name="IndWrite" type="java.lang.String"><![CDATA[1]]></Field>
	<Field name="IndWsInsert" type="java.lang.String"><![CDATA[1]]></Field>
	<Field name="IndWsSelect" type="java.lang.String"><![CDATA[1]]></Field>
	<Field name="IndWsUpdate" type="java.lang.String"><![CDATA[1]]></Field>
	<Field name="IntVersion" type="com.sunopsis.sql.DbInt"><![CDATA[1]]></Field>
	<Field name="ICol" type="com.sunopsis.sql.DbInt"><![CDATA[1645]]></Field>
	<Field name="ISrcCol" type="com.sunopsis.sql.DbInt"><![CDATA[null]]></Field>
	<Field name="ITable" type="com.sunopsis.sql.DbInt"><![CDATA[192]]></Field>
	<Field name="ITxtColDesc" type="com.sunopsis.sql.DbInt"><![CDATA[null]]></Field>
	<Field name="LastDate" type="java.sql.Timestamp"><![CDATA[2021-05-21 12:32:42.0]]></Field>
	<Field name="LastUser" type="java.lang.String"><![CDATA[prueba]]></Field>
	<Field name="Longc" type="com.sunopsis.sql.DbInt"><![CDATA[null]]></Field>
	<Field name="Pos" type="com.sunopsis.sql.DbInt"><![CDATA[16]]></Field>
	<Field name="RecCodeList" type="java.lang.String">null</Field>
	<Field name="Scalec" type="com.sunopsis.sql.DbInt"><![CDATA[null]]></Field>
	<Field name="ScdColType" type="java.lang.String">null</Field>
	<Field name="SourceDt" type="java.lang.String"><![CDATA[DATE]]></Field>
</Object>
<Object class="com.sunopsis.dwg.dbobj.SnpCol">
		<Field name="Bytes" type="com.sunopsis.sql.DbInt"><![CDATA[0]]></Field>
	<Field name="CheckFlow" type="java.lang.String"><![CDATA[1]]></Field>
	<Field name="CheckStat" type="java.lang.String"><![CDATA[0]]></Field>
	<Field name="ColDecSep" type="java.lang.String">null</Field>
	<Field name="ColFormat" type="java.lang.String">null</Field>
	<Field name="ColHeading" type="java.lang.String"><![CDATA[TIEMPO_DE_VIAJE]]></Field>
	<Field name="ColMandatory" type="java.lang.String"><![CDATA[0]]></Field>
	<Field name="ColName" type="java.lang.String"><![CDATA[TIEMPO_DE_VIAJE]]></Field>
	<Field name="ColNullIfErr" type="java.lang.String">null</Field>
	<Field name="DataFormat" type="java.lang.String">null</Field>
	<Field name="DefValue" type="java.lang.String">null</Field>
	<Field name="ExtVersion" type="java.lang.String">null</Field>
	<Field name="FilePos" type="com.sunopsis.sql.DbInt"><![CDATA[null]]></Field>
	<Field name="FirstDate" type="java.sql.Timestamp"><![CDATA[2021-05-21 12:32:43.0]]></Field>
	<Field name="FirstUser" type="java.lang.String"><![CDATA[prueba]]></Field>
	<Field name="GlobalId" type="java.lang.String"><![CDATA[17596e86-488c-48ec-ad2e-0f38eb64a557]]></Field>
	<Field name="HbaseEncoding" type="java.lang.String">null</Field>
	<Field name="HiveSortbyPos" type="com.sunopsis.sql.DbInt"><![CDATA[null]]></Field>
	<Field name="IndChange" type="java.lang.String"><![CDATA[I]]></Field>
	<Field name="IndHiveCluster" type="java.lang.String">null</Field>
	<Field name="IndHivePartition" type="java.lang.String">null</Field>
	<Field name="IndHiveSort" type="java.lang.String">null</Field>
	<Field name="IndHiveSortbyAsc" type="java.lang.String">null</Field>
	<Field name="IndIn" type="java.lang.String">null</Field>
	<Field name="IndOut" type="java.lang.String">null</Field>
	<Field name="IndWrite" type="java.lang.String"><![CDATA[1]]></Field>
	<Field name="IndWsInsert" type="java.lang.String"><![CDATA[1]]></Field>
	<Field name="IndWsSelect" type="java.lang.String"><![CDATA[1]]></Field>
	<Field name="IndWsUpdate" type="java.lang.String"><![CDATA[1]]></Field>
	<Field name="IntVersion" type="com.sunopsis.sql.DbInt"><![CDATA[1]]></Field>
	<Field name="ICol" type="com.sunopsis.sql.DbInt"><![CDATA[1660]]></Field>
	<Field name="ISrcCol" type="com.sunopsis.sql.DbInt"><![CDATA[null]]></Field>
	<Field name="ITable" type="com.sunopsis.sql.DbInt"><![CDATA[192]]></Field>
	<Field name="ITxtColDesc" type="com.sunopsis.sql.DbInt"><![CDATA[null]]></Field>
	<Field name="LastDate" type="java.sql.Timestamp"><![CDATA[2021-05-21 12:32:43.0]]></Field>
	<Field name="LastUser" type="java.lang.String"><![CDATA[prueba]]></Field>
	<Field name="Longc" type="com.sunopsis.sql.DbInt"><![CDATA[38]]></Field>
	<Field name="Pos" type="com.sunopsis.sql.DbInt"><![CDATA[17]]></Field>
	<Field name="RecCodeList" type="java.lang.String">null</Field>
	<Field name="Scalec" type="com.sunopsis.sql.DbInt"><![CDATA[0]]></Field>
	<Field name="ScdColType" type="java.lang.String">null</Field>
	<Field name="SourceDt" type="java.lang.String"><![CDATA[NUMBER]]></Field>
</Object>
<Object class="com.sunopsis.dwg.dbobj.SnpCol">
		<Field name="Bytes" type="com.sunopsis.sql.DbInt"><![CDATA[0]]></Field>
	<Field name="CheckFlow" type="java.lang.String"><![CDATA[1]]></Field>
	<Field name="CheckStat" type="java.lang.String"><![CDATA[0]]></Field>
	<Field name="ColDecSep" type="java.lang.String">null</Field>
	<Field name="ColFormat" type="java.lang.String">null</Field>
	<Field name="ColHeading" type="java.lang.String"><![CDATA[ORDEN_DE_TRABAJO]]></Field>
	<Field name="ColMandatory" type="java.lang.String"><![CDATA[0]]></Field>
	<Field name="ColName" type="java.lang.String"><![CDATA[ORDEN_DE_TRABAJO]]></Field>
	<Field name="ColNullIfErr" type="java.lang.String">null</Field>
	<Field name="DataFormat" type="java.lang.String">null</Field>
	<Field name="DefValue" type="java.lang.String">null</Field>
	<Field name="ExtVersion" type="java.lang.String">null</Field>
	<Field name="FilePos" type="com.sunopsis.sql.DbInt"><![CDATA[null]]></Field>
	<Field name="FirstDate" type="java.sql.Timestamp"><![CDATA[2021-05-21 12:32:43.0]]></Field>
	<Field name="FirstUser" type="java.lang.String"><![CDATA[prueba]]></Field>
	<Field name="GlobalId" type="java.lang.String"><![CDATA[062b3f30-b5c5-4875-bd2e-f0647fd52da3]]></Field>
	<Field name="HbaseEncoding" type="java.lang.String">null</Field>
	<Field name="HiveSortbyPos" type="com.sunopsis.sql.DbInt"><![CDATA[null]]></Field>
	<Field name="IndChange" type="java.lang.String"><![CDATA[I]]></Field>
	<Field name="IndHiveCluster" type="java.lang.String">null</Field>
	<Field name="IndHivePartition" type="java.lang.String">null</Field>
	<Field name="IndHiveSort" type="java.lang.String">null</Field>
	<Field name="IndHiveSortbyAsc" type="java.lang.String">null</Field>
	<Field name="IndIn" type="java.lang.String">null</Field>
	<Field name="IndOut" type="java.lang.String">null</Field>
	<Field name="IndWrite" type="java.lang.String"><![CDATA[1]]></Field>
	<Field name="IndWsInsert" type="java.lang.String"><![CDATA[1]]></Field>
	<Field name="IndWsSelect" type="java.lang.String"><![CDATA[1]]></Field>
	<Field name="IndWsUpdate" type="java.lang.String"><![CDATA[1]]></Field>
	<Field name="IntVersion" type="com.sunopsis.sql.DbInt"><![CDATA[1]]></Field>
	<Field name="ICol" type="com.sunopsis.sql.DbInt"><![CDATA[1656]]></Field>
	<Field name="ISrcCol" type="com.sunopsis.sql.DbInt"><![CDATA[null]]></Field>
	<Field name="ITable" type="com.sunopsis.sql.DbInt"><![CDATA[192]]></Field>
	<Field name="ITxtColDesc" type="com.sunopsis.sql.DbInt"><![CDATA[null]]></Field>
	<Field name="LastDate" type="java.sql.Timestamp"><![CDATA[2021-05-21 12:32:43.0]]></Field>
	<Field name="LastUser" type="java.lang.String"><![CDATA[prueba]]></Field>
	<Field name="Longc" type="com.sunopsis.sql.DbInt"><![CDATA[4000]]></Field>
	<Field name="Pos" type="com.sunopsis.sql.DbInt"><![CDATA[18]]></Field>
	<Field name="RecCodeList" type="java.lang.String">null</Field>
	<Field name="Scalec" type="com.sunopsis.sql.DbInt"><![CDATA[null]]></Field>
	<Field name="ScdColType" type="java.lang.String">null</Field>
	<Field name="SourceDt" type="java.lang.String"><![CDATA[VARCHAR2]]></Field>
</Object>
<Object class="com.sunopsis.dwg.dbobj.SnpCol">
		<Field name="Bytes" type="com.sunopsis.sql.DbInt"><![CDATA[0]]></Field>
	<Field name="CheckFlow" type="java.lang.String"><![CDATA[1]]></Field>
	<Field name="CheckStat" type="java.lang.String"><![CDATA[0]]></Field>
	<Field name="ColDecSep" type="java.lang.String">null</Field>
	<Field name="ColFormat" type="java.lang.String">null</Field>
	<Field name="ColHeading" type="java.lang.String"><![CDATA[SERVICIOS_OT]]></Field>
	<Field name="ColMandatory" type="java.lang.String"><![CDATA[0]]></Field>
	<Field name="ColName" type="java.lang.String"><![CDATA[SERVICIOS_OT]]></Field>
	<Field name="ColNullIfErr" type="java.lang.String">null</Field>
	<Field name="DataFormat" type="java.lang.String">null</Field>
	<Field name="DefValue" type="java.lang.String">null</Field>
	<Field name="ExtVersion" type="java.lang.String">null</Field>
	<Field name="FilePos" type="com.sunopsis.sql.DbInt"><![CDATA[null]]></Field>
	<Field name="FirstDate" type="java.sql.Timestamp"><![CDATA[2021-05-21 12:32:43.0]]></Field>
	<Field name="FirstUser" type="java.lang.String"><![CDATA[prueba]]></Field>
	<Field name="GlobalId" type="java.lang.String"><![CDATA[19de2afd-9ee5-449a-8cb5-2bb1b4118d9d]]></Field>
	<Field name="HbaseEncoding" type="java.lang.String">null</Field>
	<Field name="HiveSortbyPos" type="com.sunopsis.sql.DbInt"><![CDATA[null]]></Field>
	<Field name="IndChange" type="java.lang.String"><![CDATA[I]]></Field>
	<Field name="IndHiveCluster" type="java.lang.String">null</Field>
	<Field name="IndHivePartition" type="java.lang.String">null</Field>
	<Field name="IndHiveSort" type="java.lang.String">null</Field>
	<Field name="IndHiveSortbyAsc" type="java.lang.String">null</Field>
	<Field name="IndIn" type="java.lang.String">null</Field>
	<Field name="IndOut" type="java.lang.String">null</Field>
	<Field name="IndWrite" type="java.lang.String"><![CDATA[1]]></Field>
	<Field name="IndWsInsert" type="java.lang.String"><![CDATA[1]]></Field>
	<Field name="IndWsSelect" type="java.lang.String"><![CDATA[1]]></Field>
	<Field name="IndWsUpdate" type="java.lang.String"><![CDATA[1]]></Field>
	<Field name="IntVersion" type="com.sunopsis.sql.DbInt"><![CDATA[1]]></Field>
	<Field name="ICol" type="com.sunopsis.sql.DbInt"><![CDATA[1657]]></Field>
	<Field name="ISrcCol" type="com.sunopsis.sql.DbInt"><![CDATA[null]]></Field>
	<Field name="ITable" type="com.sunopsis.sql.DbInt"><![CDATA[192]]></Field>
	<Field name="ITxtColDesc" type="com.sunopsis.sql.DbInt"><![CDATA[null]]></Field>
	<Field name="LastDate" type="java.sql.Timestamp"><![CDATA[2021-05-21 12:32:43.0]]></Field>
	<Field name="LastUser" type="java.lang.String"><![CDATA[prueba]]></Field>
	<Field name="Longc" type="com.sunopsis.sql.DbInt"><![CDATA[4000]]></Field>
	<Field name="Pos" type="com.sunopsis.sql.DbInt"><![CDATA[19]]></Field>
	<Field name="RecCodeList" type="java.lang.String">null</Field>
	<Field name="Scalec" type="com.sunopsis.sql.DbInt"><![CDATA[null]]></Field>
	<Field name="ScdColType" type="java.lang.String">null</Field>
	<Field name="SourceDt" type="java.lang.String"><![CDATA[VARCHAR2]]></Field>
</Object>
<Object class="com.sunopsis.dwg.dbobj.SnpCol">
		<Field name="Bytes" type="com.sunopsis.sql.DbInt"><![CDATA[0]]></Field>
	<Field name="CheckFlow" type="java.lang.String"><![CDATA[1]]></Field>
	<Field name="CheckStat" type="java.lang.String"><![CDATA[0]]></Field>
	<Field name="ColDecSep" type="java.lang.String">null</Field>
	<Field name="ColFormat" type="java.lang.String">null</Field>
	<Field name="ColHeading" type="java.lang.String"><![CDATA[FECHA_DE_RUTA]]></Field>
	<Field name="ColMandatory" type="java.lang.String"><![CDATA[0]]></Field>
	<Field name="ColName" type="java.lang.String"><![CDATA[FECHA_DE_RUTA]]></Field>
	<Field name="ColNullIfErr" type="java.lang.String">null</Field>
	<Field name="DataFormat" type="java.lang.String">null</Field>
	<Field name="DefValue" type="java.lang.String">null</Field>
	<Field name="ExtVersion" type="java.lang.String">null</Field>
	<Field name="FilePos" type="com.sunopsis.sql.DbInt"><![CDATA[null]]></Field>
	<Field name="FirstDate" type="java.sql.Timestamp"><![CDATA[2021-05-21 12:32:42.0]]></Field>
	<Field name="FirstUser" type="java.lang.String"><![CDATA[prueba]]></Field>
	<Field name="GlobalId" type="java.lang.String"><![CDATA[e1dcf8e3-8a1b-4980-882e-22431d6a10fe]]></Field>
	<Field name="HbaseEncoding" type="java.lang.String">null</Field>
	<Field name="HiveSortbyPos" type="com.sunopsis.sql.DbInt"><![CDATA[null]]></Field>
	<Field name="IndChange" type="java.lang.String"><![CDATA[I]]></Field>
	<Field name="IndHiveCluster" type="java.lang.String">null</Field>
	<Field name="IndHivePartition" type="java.lang.String">null</Field>
	<Field name="IndHiveSort" type="java.lang.String">null</Field>
	<Field name="IndHiveSortbyAsc" type="java.lang.String">null</Field>
	<Field name="IndIn" type="java.lang.String">null</Field>
	<Field name="IndOut" type="java.lang.String">null</Field>
	<Field name="IndWrite" type="java.lang.String"><![CDATA[1]]></Field>
	<Field name="IndWsInsert" type="java.lang.String"><![CDATA[1]]></Field>
	<Field name="IndWsSelect" type="java.lang.String"><![CDATA[1]]></Field>
	<Field name="IndWsUpdate" type="java.lang.String"><![CDATA[1]]></Field>
	<Field name="IntVersion" type="com.sunopsis.sql.DbInt"><![CDATA[1]]></Field>
	<Field name="ICol" type="com.sunopsis.sql.DbInt"><![CDATA[1644]]></Field>
	<Field name="ISrcCol" type="com.sunopsis.sql.DbInt"><![CDATA[null]]></Field>
	<Field name="ITable" type="com.sunopsis.sql.DbInt"><![CDATA[192]]></Field>
	<Field name="ITxtColDesc" type="com.sunopsis.sql.DbInt"><![CDATA[null]]></Field>
	<Field name="LastDate" type="java.sql.Timestamp"><![CDATA[2021-05-21 12:32:42.0]]></Field>
	<Field name="LastUser" type="java.lang.String"><![CDATA[prueba]]></Field>
	<Field name="Longc" type="com.sunopsis.sql.DbInt"><![CDATA[null]]></Field>
	<Field name="Pos" type="com.sunopsis.sql.DbInt"><![CDATA[20]]></Field>
	<Field name="RecCodeList" type="java.lang.String">null</Field>
	<Field name="Scalec" type="com.sunopsis.sql.DbInt"><![CDATA[null]]></Field>
	<Field name="ScdColType" type="java.lang.String">null</Field>
	<Field name="SourceDt" type="java.lang.String"><![CDATA[DATE]]></Field>
</Object>
<Object class="com.sunopsis.dwg.dbobj.SnpCol">
		<Field name="Bytes" type="com.sunopsis.sql.DbInt"><![CDATA[0]]></Field>
	<Field name="CheckFlow" type="java.lang.String"><![CDATA[1]]></Field>
	<Field name="CheckStat" type="java.lang.String"><![CDATA[0]]></Field>
	<Field name="ColDecSep" type="java.lang.String">null</Field>
	<Field name="ColFormat" type="java.lang.String">null</Field>
	<Field name="ColHeading" type="java.lang.String"><![CDATA[HORA_DE_INICIO_NOTIFICADA_DE_]]></Field>
	<Field name="ColMandatory" type="java.lang.String"><![CDATA[0]]></Field>
	<Field name="ColName" type="java.lang.String"><![CDATA[HORA_DE_INICIO_NOTIFICADA_DE_]]></Field>
	<Field name="ColNullIfErr" type="java.lang.String">null</Field>
	<Field name="DataFormat" type="java.lang.String">null</Field>
	<Field name="DefValue" type="java.lang.String">null</Field>
	<Field name="ExtVersion" type="java.lang.String">null</Field>
	<Field name="FilePos" type="com.sunopsis.sql.DbInt"><![CDATA[null]]></Field>
	<Field name="FirstDate" type="java.sql.Timestamp"><![CDATA[2021-05-21 12:32:42.0]]></Field>
	<Field name="FirstUser" type="java.lang.String"><![CDATA[prueba]]></Field>
	<Field name="GlobalId" type="java.lang.String"><![CDATA[df4809b7-21e4-4f5f-8ff4-ed51bd45310d]]></Field>
	<Field name="HbaseEncoding" type="java.lang.String">null</Field>
	<Field name="HiveSortbyPos" type="com.sunopsis.sql.DbInt"><![CDATA[null]]></Field>
	<Field name="IndChange" type="java.lang.String"><![CDATA[I]]></Field>
	<Field name="IndHiveCluster" type="java.lang.String">null</Field>
	<Field name="IndHivePartition" type="java.lang.String">null</Field>
	<Field name="IndHiveSort" type="java.lang.String">null</Field>
	<Field name="IndHiveSortbyAsc" type="java.lang.String">null</Field>
	<Field name="IndIn" type="java.lang.String">null</Field>
	<Field name="IndOut" type="java.lang.String">null</Field>
	<Field name="IndWrite" type="java.lang.String"><![CDATA[1]]></Field>
	<Field name="IndWsInsert" type="java.lang.String"><![CDATA[1]]></Field>
	<Field name="IndWsSelect" type="java.lang.String"><![CDATA[1]]></Field>
	<Field name="IndWsUpdate" type="java.lang.String"><![CDATA[1]]></Field>
	<Field name="IntVersion" type="com.sunopsis.sql.DbInt"><![CDATA[1]]></Field>
	<Field name="ICol" type="com.sunopsis.sql.DbInt"><![CDATA[1647]]></Field>
	<Field name="ISrcCol" type="com.sunopsis.sql.DbInt"><![CDATA[null]]></Field>
	<Field name="ITable" type="com.sunopsis.sql.DbInt"><![CDATA[192]]></Field>
	<Field name="ITxtColDesc" type="com.sunopsis.sql.DbInt"><![CDATA[null]]></Field>
	<Field name="LastDate" type="java.sql.Timestamp"><![CDATA[2021-05-21 12:32:42.0]]></Field>
	<Field name="LastUser" type="java.lang.String"><![CDATA[prueba]]></Field>
	<Field name="Longc" type="com.sunopsis.sql.DbInt"><![CDATA[null]]></Field>
	<Field name="Pos" type="com.sunopsis.sql.DbInt"><![CDATA[21]]></Field>
	<Field name="RecCodeList" type="java.lang.String">null</Field>
	<Field name="Scalec" type="com.sunopsis.sql.DbInt"><![CDATA[null]]></Field>
	<Field name="ScdColType" type="java.lang.String">null</Field>
	<Field name="SourceDt" type="java.lang.String"><![CDATA[DATE]]></Field>
</Object>
<Object class="com.sunopsis.dwg.dbobj.SnpCol">
		<Field name="Bytes" type="com.sunopsis.sql.DbInt"><![CDATA[0]]></Field>
	<Field name="CheckFlow" type="java.lang.String"><![CDATA[1]]></Field>
	<Field name="CheckStat" type="java.lang.String"><![CDATA[0]]></Field>
	<Field name="ColDecSep" type="java.lang.String">null</Field>
	<Field name="ColFormat" type="java.lang.String">null</Field>
	<Field name="ColHeading" type="java.lang.String"><![CDATA[HORA_DE_FINALIZACIÓN_NOTIFIC]]></Field>
	<Field name="ColMandatory" type="java.lang.String"><![CDATA[0]]></Field>
	<Field name="ColName" type="java.lang.String"><![CDATA[HORA_DE_FINALIZACIÓN_NOTIFIC]]></Field>
	<Field name="ColNullIfErr" type="java.lang.String">null</Field>
	<Field name="DataFormat" type="java.lang.String">null</Field>
	<Field name="DefValue" type="java.lang.String">null</Field>
	<Field name="ExtVersion" type="java.lang.String">null</Field>
	<Field name="FilePos" type="com.sunopsis.sql.DbInt"><![CDATA[null]]></Field>
	<Field name="FirstDate" type="java.sql.Timestamp"><![CDATA[2021-05-21 12:32:42.0]]></Field>
	<Field name="FirstUser" type="java.lang.String"><![CDATA[prueba]]></Field>
	<Field name="GlobalId" type="java.lang.String"><![CDATA[a8aec279-ec4b-48f9-84d6-4e711378cc42]]></Field>
	<Field name="HbaseEncoding" type="java.lang.String">null</Field>
	<Field name="HiveSortbyPos" type="com.sunopsis.sql.DbInt"><![CDATA[null]]></Field>
	<Field name="IndChange" type="java.lang.String"><![CDATA[I]]></Field>
	<Field name="IndHiveCluster" type="java.lang.String">null</Field>
	<Field name="IndHivePartition" type="java.lang.String">null</Field>
	<Field name="IndHiveSort" type="java.lang.String">null</Field>
	<Field name="IndHiveSortbyAsc" type="java.lang.String">null</Field>
	<Field name="IndIn" type="java.lang.String">null</Field>
	<Field name="IndOut" type="java.lang.String">null</Field>
	<Field name="IndWrite" type="java.lang.String"><![CDATA[1]]></Field>
	<Field name="IndWsInsert" type="java.lang.String"><![CDATA[1]]></Field>
	<Field name="IndWsSelect" type="java.lang.String"><![CDATA[1]]></Field>
	<Field name="IndWsUpdate" type="java.lang.String"><![CDATA[1]]></Field>
	<Field name="IntVersion" type="com.sunopsis.sql.DbInt"><![CDATA[1]]></Field>
	<Field name="ICol" type="com.sunopsis.sql.DbInt"><![CDATA[1646]]></Field>
	<Field name="ISrcCol" type="com.sunopsis.sql.DbInt"><![CDATA[null]]></Field>
	<Field name="ITable" type="com.sunopsis.sql.DbInt"><![CDATA[192]]></Field>
	<Field name="ITxtColDesc" type="com.sunopsis.sql.DbInt"><![CDATA[null]]></Field>
	<Field name="LastDate" type="java.sql.Timestamp"><![CDATA[2021-05-21 12:32:42.0]]></Field>
	<Field name="LastUser" type="java.lang.String"><![CDATA[prueba]]></Field>
	<Field name="Longc" type="com.sunopsis.sql.DbInt"><![CDATA[null]]></Field>
	<Field name="Pos" type="com.sunopsis.sql.DbInt"><![CDATA[22]]></Field>
	<Field name="RecCodeList" type="java.lang.String">null</Field>
	<Field name="Scalec" type="com.sunopsis.sql.DbInt"><![CDATA[null]]></Field>
	<Field name="ScdColType" type="java.lang.String">null</Field>
	<Field name="SourceDt" type="java.lang.String"><![CDATA[DATE]]></Field>
</Object>
<Object class="com.sunopsis.dwg.dbobj.SnpCol">
		<Field name="Bytes" type="com.sunopsis.sql.DbInt"><![CDATA[0]]></Field>
	<Field name="CheckFlow" type="java.lang.String"><![CDATA[1]]></Field>
	<Field name="CheckStat" type="java.lang.String"><![CDATA[0]]></Field>
	<Field name="ColDecSep" type="java.lang.String">null</Field>
	<Field name="ColFormat" type="java.lang.String">null</Field>
	<Field name="ColHeading" type="java.lang.String"><![CDATA[NODO]]></Field>
	<Field name="ColMandatory" type="java.lang.String"><![CDATA[0]]></Field>
	<Field name="ColName" type="java.lang.String"><![CDATA[NODO]]></Field>
	<Field name="ColNullIfErr" type="java.lang.String">null</Field>
	<Field name="DataFormat" type="java.lang.String">null</Field>
	<Field name="DefValue" type="java.lang.String">null</Field>
	<Field name="ExtVersion" type="java.lang.String">null</Field>
	<Field name="FilePos" type="com.sunopsis.sql.DbInt"><![CDATA[null]]></Field>
	<Field name="FirstDate" type="java.sql.Timestamp"><![CDATA[2021-05-21 12:32:43.0]]></Field>
	<Field name="FirstUser" type="java.lang.String"><![CDATA[prueba]]></Field>
	<Field name="GlobalId" type="java.lang.String"><![CDATA[c486cd45-34d3-4272-ac44-58b4219b83c2]]></Field>
	<Field name="HbaseEncoding" type="java.lang.String">null</Field>
	<Field name="HiveSortbyPos" type="com.sunopsis.sql.DbInt"><![CDATA[null]]></Field>
	<Field name="IndChange" type="java.lang.String"><![CDATA[I]]></Field>
	<Field name="IndHiveCluster" type="java.lang.String">null</Field>
	<Field name="IndHivePartition" type="java.lang.String">null</Field>
	<Field name="IndHiveSort" type="java.lang.String">null</Field>
	<Field name="IndHiveSortbyAsc" type="java.lang.String">null</Field>
	<Field name="IndIn" type="java.lang.String">null</Field>
	<Field name="IndOut" type="java.lang.String">null</Field>
	<Field name="IndWrite" type="java.lang.String"><![CDATA[1]]></Field>
	<Field name="IndWsInsert" type="java.lang.String"><![CDATA[1]]></Field>
	<Field name="IndWsSelect" type="java.lang.String"><![CDATA[1]]></Field>
	<Field name="IndWsUpdate" type="java.lang.String"><![CDATA[1]]></Field>
	<Field name="IntVersion" type="com.sunopsis.sql.DbInt"><![CDATA[1]]></Field>
	<Field name="ICol" type="com.sunopsis.sql.DbInt"><![CDATA[1654]]></Field>
	<Field name="ISrcCol" type="com.sunopsis.sql.DbInt"><![CDATA[null]]></Field>
	<Field name="ITable" type="com.sunopsis.sql.DbInt"><![CDATA[192]]></Field>
	<Field name="ITxtColDesc" type="com.sunopsis.sql.DbInt"><![CDATA[null]]></Field>
	<Field name="LastDate" type="java.sql.Timestamp"><![CDATA[2021-05-21 12:32:43.0]]></Field>
	<Field name="LastUser" type="java.lang.String"><![CDATA[prueba]]></Field>
	<Field name="Longc" type="com.sunopsis.sql.DbInt"><![CDATA[4000]]></Field>
	<Field name="Pos" type="com.sunopsis.sql.DbInt"><![CDATA[23]]></Field>
	<Field name="RecCodeList" type="java.lang.String">null</Field>
	<Field name="Scalec" type="com.sunopsis.sql.DbInt"><![CDATA[null]]></Field>
	<Field name="ScdColType" type="java.lang.String">null</Field>
	<Field name="SourceDt" type="java.lang.String"><![CDATA[VARCHAR2]]></Field>
</Object>
<Object class="com.sunopsis.dwg.dbobj.SnpCol">
		<Field name="Bytes" type="com.sunopsis.sql.DbInt"><![CDATA[0]]></Field>
	<Field name="CheckFlow" type="java.lang.String"><![CDATA[1]]></Field>
	<Field name="CheckStat" type="java.lang.String"><![CDATA[0]]></Field>
	<Field name="ColDecSep" type="java.lang.String">null</Field>
	<Field name="ColFormat" type="java.lang.String">null</Field>
	<Field name="ColHeading" type="java.lang.String"><![CDATA[TIPO_DE_RED]]></Field>
	<Field name="ColMandatory" type="java.lang.String"><![CDATA[0]]></Field>
	<Field name="ColName" type="java.lang.String"><![CDATA[TIPO_DE_RED]]></Field>
	<Field name="ColNullIfErr" type="java.lang.String">null</Field>
	<Field name="DataFormat" type="java.lang.String">null</Field>
	<Field name="DefValue" type="java.lang.String">null</Field>
	<Field name="ExtVersion" type="java.lang.String">null</Field>
	<Field name="FilePos" type="com.sunopsis.sql.DbInt"><![CDATA[null]]></Field>
	<Field name="FirstDate" type="java.sql.Timestamp"><![CDATA[2021-05-21 12:32:43.0]]></Field>
	<Field name="FirstUser" type="java.lang.String"><![CDATA[prueba]]></Field>
	<Field name="GlobalId" type="java.lang.String"><![CDATA[dee0deec-226a-448b-b346-4d21d88eef57]]></Field>
	<Field name="HbaseEncoding" type="java.lang.String">null</Field>
	<Field name="HiveSortbyPos" type="com.sunopsis.sql.DbInt"><![CDATA[null]]></Field>
	<Field name="IndChange" type="java.lang.String"><![CDATA[I]]></Field>
	<Field name="IndHiveCluster" type="java.lang.String">null</Field>
	<Field name="IndHivePartition" type="java.lang.String">null</Field>
	<Field name="IndHiveSort" type="java.lang.String">null</Field>
	<Field name="IndHiveSortbyAsc" type="java.lang.String">null</Field>
	<Field name="IndIn" type="java.lang.String">null</Field>
	<Field name="IndOut" type="java.lang.String">null</Field>
	<Field name="IndWrite" type="java.lang.String"><![CDATA[1]]></Field>
	<Field name="IndWsInsert" type="java.lang.String"><![CDATA[1]]></Field>
	<Field name="IndWsSelect" type="java.lang.String"><![CDATA[1]]></Field>
	<Field name="IndWsUpdate" type="java.lang.String"><![CDATA[1]]></Field>
	<Field name="IntVersion" type="com.sunopsis.sql.DbInt"><![CDATA[1]]></Field>
	<Field name="ICol" type="com.sunopsis.sql.DbInt"><![CDATA[1661]]></Field>
	<Field name="ISrcCol" type="com.sunopsis.sql.DbInt"><![CDATA[null]]></Field>
	<Field name="ITable" type="com.sunopsis.sql.DbInt"><![CDATA[192]]></Field>
	<Field name="ITxtColDesc" type="com.sunopsis.sql.DbInt"><![CDATA[null]]></Field>
	<Field name="LastDate" type="java.sql.Timestamp"><![CDATA[2021-05-21 12:32:43.0]]></Field>
	<Field name="LastUser" type="java.lang.String"><![CDATA[prueba]]></Field>
	<Field name="Longc" type="com.sunopsis.sql.DbInt"><![CDATA[4000]]></Field>
	<Field name="Pos" type="com.sunopsis.sql.DbInt"><![CDATA[24]]></Field>
	<Field name="RecCodeList" type="java.lang.String">null</Field>
	<Field name="Scalec" type="com.sunopsis.sql.DbInt"><![CDATA[null]]></Field>
	<Field name="ScdColType" type="java.lang.String">null</Field>
	<Field name="SourceDt" type="java.lang.String"><![CDATA[VARCHAR2]]></Field>
</Object>
<Object class="com.sunopsis.dwg.dbobj.SnpCol">
		<Field name="Bytes" type="com.sunopsis.sql.DbInt"><![CDATA[0]]></Field>
	<Field name="CheckFlow" type="java.lang.String"><![CDATA[1]]></Field>
	<Field name="CheckStat" type="java.lang.String"><![CDATA[0]]></Field>
	<Field name="ColDecSep" type="java.lang.String">null</Field>
	<Field name="ColFormat" type="java.lang.String">null</Field>
	<Field name="ColHeading" type="java.lang.String"><![CDATA[SUBTIPO_DE_CLIENTE_SUBSEGMENT]]></Field>
	<Field name="ColMandatory" type="java.lang.String"><![CDATA[0]]></Field>
	<Field name="ColName" type="java.lang.String"><![CDATA[SUBTIPO_DE_CLIENTE_SUBSEGMENT]]></Field>
	<Field name="ColNullIfErr" type="java.lang.String">null</Field>
	<Field name="DataFormat" type="java.lang.String">null</Field>
	<Field name="DefValue" type="java.lang.String">null</Field>
	<Field name="ExtVersion" type="java.lang.String">null</Field>
	<Field name="FilePos" type="com.sunopsis.sql.DbInt"><![CDATA[null]]></Field>
	<Field name="FirstDate" type="java.sql.Timestamp"><![CDATA[2021-05-21 12:32:43.0]]></Field>
	<Field name="FirstUser" type="java.lang.String"><![CDATA[prueba]]></Field>
	<Field name="GlobalId" type="java.lang.String"><![CDATA[abb62a86-77ae-4514-9c2b-7fe3d66aa156]]></Field>
	<Field name="HbaseEncoding" type="java.lang.String">null</Field>
	<Field name="HiveSortbyPos" type="com.sunopsis.sql.DbInt"><![CDATA[null]]></Field>
	<Field name="IndChange" type="java.lang.String"><![CDATA[I]]></Field>
	<Field name="IndHiveCluster" type="java.lang.String">null</Field>
	<Field name="IndHivePartition" type="java.lang.String">null</Field>
	<Field name="IndHiveSort" type="java.lang.String">null</Field>
	<Field name="IndHiveSortbyAsc" type="java.lang.String">null</Field>
	<Field name="IndIn" type="java.lang.String">null</Field>
	<Field name="IndOut" type="java.lang.String">null</Field>
	<Field name="IndWrite" type="java.lang.String"><![CDATA[1]]></Field>
	<Field name="IndWsInsert" type="java.lang.String"><![CDATA[1]]></Field>
	<Field name="IndWsSelect" type="java.lang.String"><![CDATA[1]]></Field>
	<Field name="IndWsUpdate" type="java.lang.String"><![CDATA[1]]></Field>
	<Field name="IntVersion" type="com.sunopsis.sql.DbInt"><![CDATA[1]]></Field>
	<Field name="ICol" type="com.sunopsis.sql.DbInt"><![CDATA[1658]]></Field>
	<Field name="ISrcCol" type="com.sunopsis.sql.DbInt"><![CDATA[null]]></Field>
	<Field name="ITable" type="com.sunopsis.sql.DbInt"><![CDATA[192]]></Field>
	<Field name="ITxtColDesc" type="com.sunopsis.sql.DbInt"><![CDATA[null]]></Field>
	<Field name="LastDate" type="java.sql.Timestamp"><![CDATA[2021-05-21 12:32:43.0]]></Field>
	<Field name="LastUser" type="java.lang.String"><![CDATA[prueba]]></Field>
	<Field name="Longc" type="com.sunopsis.sql.DbInt"><![CDATA[4000]]></Field>
	<Field name="Pos" type="com.sunopsis.sql.DbInt"><![CDATA[25]]></Field>
	<Field name="RecCodeList" type="java.lang.String">null</Field>
	<Field name="Scalec" type="com.sunopsis.sql.DbInt"><![CDATA[null]]></Field>
	<Field name="ScdColType" type="java.lang.String">null</Field>
	<Field name="SourceDt" type="java.lang.String"><![CDATA[VARCHAR2]]></Field>
</Object>
<Object class="com.sunopsis.dwg.dbobj.SnpCol">
		<Field name="Bytes" type="com.sunopsis.sql.DbInt"><![CDATA[0]]></Field>
	<Field name="CheckFlow" type="java.lang.String"><![CDATA[1]]></Field>
	<Field name="CheckStat" type="java.lang.String"><![CDATA[0]]></Field>
	<Field name="ColDecSep" type="java.lang.String">null</Field>
	<Field name="ColFormat" type="java.lang.String">null</Field>
	<Field name="ColHeading" type="java.lang.String"><![CDATA[BILLING_ACTIVITIES_REPORTED]]></Field>
	<Field name="ColMandatory" type="java.lang.String"><![CDATA[0]]></Field>
	<Field name="ColName" type="java.lang.String"><![CDATA[BILLING_ACTIVITIES_REPORTED]]></Field>
	<Field name="ColNullIfErr" type="java.lang.String">null</Field>
	<Field name="DataFormat" type="java.lang.String">null</Field>
	<Field name="DefValue" type="java.lang.String">null</Field>
	<Field name="ExtVersion" type="java.lang.String">null</Field>
	<Field name="FilePos" type="com.sunopsis.sql.DbInt"><![CDATA[null]]></Field>
	<Field name="FirstDate" type="java.sql.Timestamp"><![CDATA[2021-05-21 12:32:42.0]]></Field>
	<Field name="FirstUser" type="java.lang.String"><![CDATA[prueba]]></Field>
	<Field name="GlobalId" type="java.lang.String"><![CDATA[d6c08e5f-c5c4-4f20-9e51-e2e5a81db3ba]]></Field>
	<Field name="HbaseEncoding" type="java.lang.String">null</Field>
	<Field name="HiveSortbyPos" type="com.sunopsis.sql.DbInt"><![CDATA[null]]></Field>
	<Field name="IndChange" type="java.lang.String"><![CDATA[I]]></Field>
	<Field name="IndHiveCluster" type="java.lang.String">null</Field>
	<Field name="IndHivePartition" type="java.lang.String">null</Field>
	<Field name="IndHiveSort" type="java.lang.String">null</Field>
	<Field name="IndHiveSortbyAsc" type="java.lang.String">null</Field>
	<Field name="IndIn" type="java.lang.String">null</Field>
	<Field name="IndOut" type="java.lang.String">null</Field>
	<Field name="IndWrite" type="java.lang.String"><![CDATA[1]]></Field>
	<Field name="IndWsInsert" type="java.lang.String"><![CDATA[1]]></Field>
	<Field name="IndWsSelect" type="java.lang.String"><![CDATA[1]]></Field>
	<Field name="IndWsUpdate" type="java.lang.String"><![CDATA[1]]></Field>
	<Field name="IntVersion" type="com.sunopsis.sql.DbInt"><![CDATA[1]]></Field>
	<Field name="ICol" type="com.sunopsis.sql.DbInt"><![CDATA[1637]]></Field>
	<Field name="ISrcCol" type="com.sunopsis.sql.DbInt"><![CDATA[null]]></Field>
	<Field name="ITable" type="com.sunopsis.sql.DbInt"><![CDATA[192]]></Field>
	<Field name="ITxtColDesc" type="com.sunopsis.sql.DbInt"><![CDATA[null]]></Field>
	<Field name="LastDate" type="java.sql.Timestamp"><![CDATA[2021-05-21 12:32:42.0]]></Field>
	<Field name="LastUser" type="java.lang.String"><![CDATA[prueba]]></Field>
	<Field name="Longc" type="com.sunopsis.sql.DbInt"><![CDATA[4000]]></Field>
	<Field name="Pos" type="com.sunopsis.sql.DbInt"><![CDATA[26]]></Field>
	<Field name="RecCodeList" type="java.lang.String">null</Field>
	<Field name="Scalec" type="com.sunopsis.sql.DbInt"><![CDATA[null]]></Field>
	<Field name="ScdColType" type="java.lang.String">null</Field>
	<Field name="SourceDt" type="java.lang.String"><![CDATA[VARCHAR2]]></Field>
</Object>
<Object class="com.sunopsis.dwg.dbobj.SnpCol">
		<Field name="Bytes" type="com.sunopsis.sql.DbInt"><![CDATA[0]]></Field>
	<Field name="CheckFlow" type="java.lang.String"><![CDATA[1]]></Field>
	<Field name="CheckStat" type="java.lang.String"><![CDATA[0]]></Field>
	<Field name="ColDecSep" type="java.lang.String">null</Field>
	<Field name="ColFormat" type="java.lang.String">null</Field>
	<Field name="ColHeading" type="java.lang.String"><![CDATA[BILLING_ACTIVITIES_REPLACEMEN]]></Field>
	<Field name="ColMandatory" type="java.lang.String"><![CDATA[0]]></Field>
	<Field name="ColName" type="java.lang.String"><![CDATA[BILLING_ACTIVITIES_REPLACEMEN]]></Field>
	<Field name="ColNullIfErr" type="java.lang.String">null</Field>
	<Field name="DataFormat" type="java.lang.String">null</Field>
	<Field name="DefValue" type="java.lang.String">null</Field>
	<Field name="ExtVersion" type="java.lang.String">null</Field>
	<Field name="FilePos" type="com.sunopsis.sql.DbInt"><![CDATA[null]]></Field>
	<Field name="FirstDate" type="java.sql.Timestamp"><![CDATA[2021-05-21 12:32:42.0]]></Field>
	<Field name="FirstUser" type="java.lang.String"><![CDATA[prueba]]></Field>
	<Field name="GlobalId" type="java.lang.String"><![CDATA[cdb044bf-c667-4ea1-a9de-2e24b8de673f]]></Field>
	<Field name="HbaseEncoding" type="java.lang.String">null</Field>
	<Field name="HiveSortbyPos" type="com.sunopsis.sql.DbInt"><![CDATA[null]]></Field>
	<Field name="IndChange" type="java.lang.String"><![CDATA[I]]></Field>
	<Field name="IndHiveCluster" type="java.lang.String">null</Field>
	<Field name="IndHivePartition" type="java.lang.String">null</Field>
	<Field name="IndHiveSort" type="java.lang.String">null</Field>
	<Field name="IndHiveSortbyAsc" type="java.lang.String">null</Field>
	<Field name="IndIn" type="java.lang.String">null</Field>
	<Field name="IndOut" type="java.lang.String">null</Field>
	<Field name="IndWrite" type="java.lang.String"><![CDATA[1]]></Field>
	<Field name="IndWsInsert" type="java.lang.String"><![CDATA[1]]></Field>
	<Field name="IndWsSelect" type="java.lang.String"><![CDATA[1]]></Field>
	<Field name="IndWsUpdate" type="java.lang.String"><![CDATA[1]]></Field>
	<Field name="IntVersion" type="com.sunopsis.sql.DbInt"><![CDATA[1]]></Field>
	<Field name="ICol" type="com.sunopsis.sql.DbInt"><![CDATA[1636]]></Field>
	<Field name="ISrcCol" type="com.sunopsis.sql.DbInt"><![CDATA[null]]></Field>
	<Field name="ITable" type="com.sunopsis.sql.DbInt"><![CDATA[192]]></Field>
	<Field name="ITxtColDesc" type="com.sunopsis.sql.DbInt"><![CDATA[null]]></Field>
	<Field name="LastDate" type="java.sql.Timestamp"><![CDATA[2021-05-21 12:32:42.0]]></Field>
	<Field name="LastUser" type="java.lang.String"><![CDATA[prueba]]></Field>
	<Field name="Longc" type="com.sunopsis.sql.DbInt"><![CDATA[4000]]></Field>
	<Field name="Pos" type="com.sunopsis.sql.DbInt"><![CDATA[27]]></Field>
	<Field name="RecCodeList" type="java.lang.String">null</Field>
	<Field name="Scalec" type="com.sunopsis.sql.DbInt"><![CDATA[null]]></Field>
	<Field name="ScdColType" type="java.lang.String">null</Field>
	<Field name="SourceDt" type="java.lang.String"><![CDATA[VARCHAR2]]></Field>
</Object>
<Object class="com.sunopsis.dwg.dbobj.SnpCol">
		<Field name="Bytes" type="com.sunopsis.sql.DbInt"><![CDATA[0]]></Field>
	<Field name="CheckFlow" type="java.lang.String"><![CDATA[1]]></Field>
	<Field name="CheckStat" type="java.lang.String"><![CDATA[0]]></Field>
	<Field name="ColDecSep" type="java.lang.String">null</Field>
	<Field name="ColFormat" type="java.lang.String">null</Field>
	<Field name="ColHeading" type="java.lang.String"><![CDATA[ACTIVITY_ID]]></Field>
	<Field name="ColMandatory" type="java.lang.String"><![CDATA[0]]></Field>
	<Field name="ColName" type="java.lang.String"><![CDATA[ACTIVITY_ID]]></Field>
	<Field name="ColNullIfErr" type="java.lang.String">null</Field>
	<Field name="DataFormat" type="java.lang.String">null</Field>
	<Field name="DefValue" type="java.lang.String">null</Field>
	<Field name="ExtVersion" type="java.lang.String">null</Field>
	<Field name="FilePos" type="com.sunopsis.sql.DbInt"><![CDATA[null]]></Field>
	<Field name="FirstDate" type="java.sql.Timestamp"><![CDATA[2021-05-21 12:32:42.0]]></Field>
	<Field name="FirstUser" type="java.lang.String"><![CDATA[prueba]]></Field>
	<Field name="GlobalId" type="java.lang.String"><![CDATA[7b36ec90-91a2-496c-9067-9f61b177b85d]]></Field>
	<Field name="HbaseEncoding" type="java.lang.String">null</Field>
	<Field name="HiveSortbyPos" type="com.sunopsis.sql.DbInt"><![CDATA[null]]></Field>
	<Field name="IndChange" type="java.lang.String"><![CDATA[I]]></Field>
	<Field name="IndHiveCluster" type="java.lang.String">null</Field>
	<Field name="IndHivePartition" type="java.lang.String">null</Field>
	<Field name="IndHiveSort" type="java.lang.String">null</Field>
	<Field name="IndHiveSortbyAsc" type="java.lang.String">null</Field>
	<Field name="IndIn" type="java.lang.String">null</Field>
	<Field name="IndOut" type="java.lang.String">null</Field>
	<Field name="IndWrite" type="java.lang.String"><![CDATA[1]]></Field>
	<Field name="IndWsInsert" type="java.lang.String"><![CDATA[1]]></Field>
	<Field name="IndWsSelect" type="java.lang.String"><![CDATA[1]]></Field>
	<Field name="IndWsUpdate" type="java.lang.String"><![CDATA[1]]></Field>
	<Field name="IntVersion" type="com.sunopsis.sql.DbInt"><![CDATA[1]]></Field>
	<Field name="ICol" type="com.sunopsis.sql.DbInt"><![CDATA[1635]]></Field>
	<Field name="ISrcCol" type="com.sunopsis.sql.DbInt"><![CDATA[null]]></Field>
	<Field name="ITable" type="com.sunopsis.sql.DbInt"><![CDATA[192]]></Field>
	<Field name="ITxtColDesc" type="com.sunopsis.sql.DbInt"><![CDATA[null]]></Field>
	<Field name="LastDate" type="java.sql.Timestamp"><![CDATA[2021-05-21 12:32:42.0]]></Field>
	<Field name="LastUser" type="java.lang.String"><![CDATA[prueba]]></Field>
	<Field name="Longc" type="com.sunopsis.sql.DbInt"><![CDATA[38]]></Field>
	<Field name="Pos" type="com.sunopsis.sql.DbInt"><![CDATA[28]]></Field>
	<Field name="RecCodeList" type="java.lang.String">null</Field>
	<Field name="Scalec" type="com.sunopsis.sql.DbInt"><![CDATA[0]]></Field>
	<Field name="ScdColType" type="java.lang.String">null</Field>
	<Field name="SourceDt" type="java.lang.String"><![CDATA[NUMBER]]></Field>
</Object>
<Object class="com.sunopsis.dwg.dbobj.SnpFKXRef">
		<Field name="RefKey" type="java.lang.String"><![CDATA[SNP_SUBMODEL.51.52]]></Field>
	<Field name="RefObjGlobalId" type="java.lang.String"><![CDATA[7bcc40ac-bdb1-4272-a962-ae3f42057754]]></Field>
 <Field name="RefObjFQName" type="java.lang.String"><![CDATA[prueba.Global]]></Field>
 <Field name="RefObjFQType" type="java.lang.String"><![CDATA[SNP_MODEL.SNP_SUBMODEL]]></Field>
 <Field name="RefObjFQNameLengths" type="java.lang.String"><![CDATA[6.6]]></Field>
</Object>
<Object class="com.sunopsis.dwg.dbobj.SnpFKXRef">
		<Field name="RefKey" type="java.lang.String"><![CDATA[SNP_TABLE.192]]></Field>
	<Field name="RefObjGlobalId" type="java.lang.String"><![CDATA[394df076-b99a-4538-b912-2f93e9919712]]></Field>
 <Field name="RefObjFQName" type="java.lang.String"><![CDATA[prueba.Global.ACTIVIDADESBK]]></Field>
 <Field name="RefObjFQType" type="java.lang.String"><![CDATA[SNP_MODEL.SNP_SUBMODEL.SNP_TABLE]]></Field>
 <Field name="RefObjFQNameLengths" type="java.lang.String"><![CDATA[6.6.13]]></Field>
</Object>
<Object class="com.sunopsis.dwg.DwgExportSummary">
		<Field name="ExpTxtNb" type="com.sunopsis.sql.DbInt"><![CDATA[0]]></Field>
	<Field name="InstObjNb" type="com.sunopsis.sql.DbInt"><![CDATA[0]]></Field>
	<Field name="JoinColNb" type="com.sunopsis.sql.DbInt"><![CDATA[0]]></Field>
	<Field name="JoinNb" type="com.sunopsis.sql.DbInt"><![CDATA[0]]></Field>
	<Field name="KeyColNb" type="com.sunopsis.sql.DbInt"><![CDATA[0]]></Field>
	<Field name="KeyNb" type="com.sunopsis.sql.DbInt"><![CDATA[0]]></Field>
	<Field name="LinkDiagNb" type="com.sunopsis.sql.DbInt"><![CDATA[0]]></Field>
	<Field name="MorigTxtNb" type="com.sunopsis.sql.DbInt"><![CDATA[0]]></Field>
	<Field name="MtxtNb" type="com.sunopsis.sql.DbInt"><![CDATA[0]]></Field>
	<Field name="OrigTxtNb" type="com.sunopsis.sql.DbInt"><![CDATA[0]]></Field>
	<Field name="OtherObjectsNb" type="com.sunopsis.sql.DbInt"><![CDATA[29]]></Field>
	<Field name="PlanAgentNb" type="com.sunopsis.sql.DbInt"><![CDATA[0]]></Field>
	<Field name="StepNb" type="com.sunopsis.sql.DbInt"><![CDATA[0]]></Field>
	<Field name="TxtNb" type="com.sunopsis.sql.DbInt"><![CDATA[0]]></Field>
	<Field name="UeOrigNb" type="com.sunopsis.sql.DbInt"><![CDATA[0]]></Field>
	<Field name="UeUsedNb" type="com.sunopsis.sql.DbInt"><![CDATA[0]]></Field>
	<Field name="VarPlanAgentNb" type="com.sunopsis.sql.DbInt"><![CDATA[0]]></Field>
	<Field name="ScenTxtNb" type="com.sunopsis.sql.DbInt"><![CDATA[0]]></Field>
	<Field name="OdiVersion" type="java.lang.String"><![CDATA[12.2.1]]></Field>
	<Field name="OriginRepositoryID" type="com.sunopsis.sql.DbInt"><![CDATA[11]]></Field>
	<Field name="RepositoryVersion" type="java.lang.String"><![CDATA[05.02.02.09]]></Field>
</Object>
</SunopsisExport>
